Workbook

Sheet 前提条件
A1: 収支計画計算書 — 前提条件(入力シート)
A2: 黄色のセルだけ入力してください。緑のセルと他のシートはすべて自動計算されます。
A4: ■ 建築計画
A5: 棟数(戸数) | B5: 3 | C5: 棟 | D5: アパートの場合は戸数として使用
A6: 建築費(1棟・1戸あたり) | B6: 17000000 | C6: 円 | D6: 本体工事費(税込)
A7: 外構・諸費用(総額) | B7: 3000000 | C7: 円 | D7: 外構・水道加入・登記・火災保険初回等
A8: 総事業費 | B8: =B5*B6+B7 | C8: 円
A10: ■ 資金計画
A11: 自己資金 | B11: 10000000 | C11: 円 | D11: 推奨: 総事業費の2割
A12: 借入額 | B12: =B8-B11 | C12: 円
A13: 借入金利(年利) | B13: 0.02 | D13: 変動の場合は現行金利。サマリーで+1%/+2%も自動比較
A14: 返済期間 | B14: 25 | C14: 年 | D14: 元利均等返済を想定
A15: 年間返済額 | B15: =IF(B12<=0,0,PMT(B13/12,B14*12,-B12)*12) | C15: 円/年
A17: ■ 収入計画
A18: 月額家賃(1棟・1戸あたり) | B18: 85000 | C18: 円/月 | D18: 周辺成約事例に基づき設定
A19: 満室時 年間家賃収入 | B19: =B5*B18*12 | C19: 円/年
A20: 空室率(1〜15年目) | B20: 0.05 | D20: 戸建賃貸は5%程度が目安
A21: 空室率(16年目以降) | B21: 0.1 | D21: 築年数経過による上昇を織り込み
A22: 家賃下落率(年) | B22: 0.01 | D22: 毎年この率で逓減させる保守的前提
A24: ■ 運営費
A25: 管理委託料率(実効家賃に対し) | B25: 0.05 | D25: 一般管理委託の相場 3〜5%
A26: 固定資産税・都市計画税(年) | B26: 350000 | C26: 円/年 | D26: 建物+住宅用地特例後の土地分
A27: 火災保険・その他経費(年) | B27: 100000 | C27: 円/年
A28: 小修繕・原状回復費(年) | B28: 100000 | C28: 円/年 | D28: 大規模修繕とは別枠。二重計上しないこと
A29: 大規模修繕①(実施年/金額) | B29: 12 | C29: 4500000 | D29: 外壁・屋根等 (例:150万円×3棟)
A30: 大規模修繕②(実施年/金額) | B30: 24 | C30: 4500000 | D30: 設備更新等
A32: ■ 税金(概算用)
A33: 減価償却対象(建物本体) | B33: =B5*B6 | C33: 円 | D33: 外構等は簡便化のため除外
A34: 償却率(木造・法定22年 定額法) | B34: 0.046 | D34: 軽量鉄骨等の場合は変更
A35: 所得税+住民税の適用税率(概算) | B35: 0.3 | D35: 他の所得と合算した実効税率の目安
A37: ※ 本シートは概算シミュレーションです。税務の取扱いは税理士にご確認ください。

Sheet 収支計画30年
A1: 30年 収支計画計算書(自動計算)
A2: 前提条件シートの黄色セルを変更すると、本シートは自動で再計算されます。金額単位: 円
A3: 年次 | B3: 満室時 家賃収入 | C3: 空室損 | D3: 実効 家賃収入 | E3: 管理料 | F3: 固都税 | G3: 保険 その他 | H3: 小修繕・ 原状回復 | I3: 大規模 修繕 | J3: 運営費 計 | K3: 営業純収益 (NOI) | L3: 借入返済額 (元利) | M3: (うち利息) | N3: 税引前 キャッシュフロー | O3: 減価償却費 (参考) | P3: 不動産所得 (概算) | Q3: 税金 (概算) | R3: 税引後 キャッシュフロー | S3: 累計 キャッシュフロー
A4: 1 | B4: ='前提条件'!$B$19*(1-'前提条件'!$B$22)^(A4-1) | C4: =-B4*IF(A4>=16,'前提条件'!$B$21,'前提条件'!$B$20) | D4: =B4+C4 | E4: =-D4*'前提条件'!$B$25 | F4: =-'前提条件'!$B$26 | G4: =-'前提条件'!$B$27 | H4: =-'前提条件'!$B$28 | I4: =-IF(A4='前提条件'!$B$29,'前提条件'!$C$29,0)-IF(A4='前提条件'!$B$30,'前提条件'!$C$30,0) | J4: =SUM(E4:I4) | K4: =D4+J4 | L4: =-IF(A4<='前提条件'!$B$14,'前提条件'!$B$15,0) | M4: =IF(OR(A4>'前提条件'!$B$14,'前提条件'!$B$12<=0,'前提条件'!$B$13<=0),0,CUMIPMT('前提条件'!$B$13/12,'前提条件'!$B$14*12,'前提条件'!$B$12,(A4-1)*12+1,A4*12,0)) | N4: =K4+L4 | O4: =IF(A4<=22,'前提条件'!$B$33*'前提条件'!$B$34,0) | P4: =K4+M4-O4 | Q4: =-MAX(0,P4*'前提条件'!$B$35) | R4: =N4+Q4 | S4: =R4
A5: 2 | B5: ='前提条件'!$B$19*(1-'前提条件'!$B$22)^(A5-1) | C5: =-B5*IF(A5>=16,'前提条件'!$B$21,'前提条件'!$B$20) | D5: =B5+C5 | E5: =-D5*'前提条件'!$B$25 | F5: =-'前提条件'!$B$26 | G5: =-'前提条件'!$B$27 | H5: =-'前提条件'!$B$28 | I5: =-IF(A5='前提条件'!$B$29,'前提条件'!$C$29,0)-IF(A5='前提条件'!$B$30,'前提条件'!$C$30,0) | J5: =SUM(E5:I5) | K5: =D5+J5 | L5: =-IF(A5<='前提条件'!$B$14,'前提条件'!$B$15,0) | M5: =IF(OR(A5>'前提条件'!$B$14,'前提条件'!$B$12<=0,'前提条件'!$B$13<=0),0,CUMIPMT('前提条件'!$B$13/12,'前提条件'!$B$14*12,'前提条件'!$B$12,(A5-1)*12+1,A5*12,0)) | N5: =K5+L5 | O5: =IF(A5<=22,'前提条件'!$B$33*'前提条件'!$B$34,0) | P5: =K5+M5-O5 | Q5: =-MAX(0,P5*'前提条件'!$B$35) | R5: =N5+Q5 | S5: =S4+R5
A6: 3 | B6: ='前提条件'!$B$19*(1-'前提条件'!$B$22)^(A6-1) | C6: =-B6*IF(A6>=16,'前提条件'!$B$21,'前提条件'!$B$20) | D6: =B6+C6 | E6: =-D6*'前提条件'!$B$25 | F6: =-'前提条件'!$B$26 | G6: =-'前提条件'!$B$27 | H6: =-'前提条件'!$B$28 | I6: =-IF(A6='前提条件'!$B$29,'前提条件'!$C$29,0)-IF(A6='前提条件'!$B$30,'前提条件'!$C$30,0) | J6: =SUM(E6:I6) | K6: =D6+J6 | L6: =-IF(A6<='前提条件'!$B$14,'前提条件'!$B$15,0) | M6: =IF(OR(A6>'前提条件'!$B$14,'前提条件'!$B$12<=0,'前提条件'!$B$13<=0),0,CUMIPMT('前提条件'!$B$13/12,'前提条件'!$B$14*12,'前提条件'!$B$12,(A6-1)*12+1,A6*12,0)) | N6: =K6+L6 | O6: =IF(A6<=22,'前提条件'!$B$33*'前提条件'!$B$34,0) | P6: =K6+M6-O6 | Q6: =-MAX(0,P6*'前提条件'!$B$35) | R6: =N6+Q6 | S6: =S5+R6
A7: 4 | B7: ='前提条件'!$B$19*(1-'前提条件'!$B$22)^(A7-1) | C7: =-B7*IF(A7>=16,'前提条件'!$B$21,'前提条件'!$B$20) | D7: =B7+C7 | E7: =-D7*'前提条件'!$B$25 | F7: =-'前提条件'!$B$26 | G7: =-'前提条件'!$B$27 | H7: =-'前提条件'!$B$28 | I7: =-IF(A7='前提条件'!$B$29,'前提条件'!$C$29,0)-IF(A7='前提条件'!$B$30,'前提条件'!$C$30,0) | J7: =SUM(E7:I7) | K7: =D7+J7 | L7: =-IF(A7<='前提条件'!$B$14,'前提条件'!$B$15,0) | M7: =IF(OR(A7>'前提条件'!$B$14,'前提条件'!$B$12<=0,'前提条件'!$B$13<=0),0,CUMIPMT('前提条件'!$B$13/12,'前提条件'!$B$14*12,'前提条件'!$B$12,(A7-1)*12+1,A7*12,0)) | N7: =K7+L7 | O7: =IF(A7<=22,'前提条件'!$B$33*'前提条件'!$B$34,0) | P7: =K7+M7-O7 | Q7: =-MAX(0,P7*'前提条件'!$B$35) | R7: =N7+Q7 | S7: =S6+R7
A8: 5 | B8: ='前提条件'!$B$19*(1-'前提条件'!$B$22)^(A8-1) | C8: =-B8*IF(A8>=16,'前提条件'!$B$21,'前提条件'!$B$20) | D8: =B8+C8 | E8: =-D8*'前提条件'!$B$25 | F8: =-'前提条件'!$B$26 | G8: =-'前提条件'!$B$27 | H8: =-'前提条件'!$B$28 | I8: =-IF(A8='前提条件'!$B$29,'前提条件'!$C$29,0)-IF(A8='前提条件'!$B$30,'前提条件'!$C$30,0) | J8: =SUM(E8:I8) | K8: =D8+J8 | L8: =-IF(A8<='前提条件'!$B$14,'前提条件'!$B$15,0) | M8: =IF(OR(A8>'前提条件'!$B$14,'前提条件'!$B$12<=0,'前提条件'!$B$13<=0),0,CUMIPMT('前提条件'!$B$13/12,'前提条件'!$B$14*12,'前提条件'!$B$12,(A8-1)*12+1,A8*12,0)) | N8: =K8+L8 | O8: =IF(A8<=22,'前提条件'!$B$33*'前提条件'!$B$34,0) | P8: =K8+M8-O8 | Q8: =-MAX(0,P8*'前提条件'!$B$35) | R8: =N8+Q8 | S8: =S7+R8
A9: 6 | B9: ='前提条件'!$B$19*(1-'前提条件'!$B$22)^(A9-1) | C9: =-B9*IF(A9>=16,'前提条件'!$B$21,'前提条件'!$B$20) | D9: =B9+C9 | E9: =-D9*'前提条件'!$B$25 | F9: =-'前提条件'!$B$26 | G9: =-'前提条件'!$B$27 | H9: =-'前提条件'!$B$28 | I9: =-IF(A9='前提条件'!$B$29,'前提条件'!$C$29,0)-IF(A9='前提条件'!$B$30,'前提条件'!$C$30,0) | J9: =SUM(E9:I9) | K9: =D9+J9 | L9: =-IF(A9<='前提条件'!$B$14,'前提条件'!$B$15,0) | M9: =IF(OR(A9>'前提条件'!$B$14,'前提条件'!$B$12<=0,'前提条件'!$B$13<=0),0,CUMIPMT('前提条件'!$B$13/12,'前提条件'!$B$14*12,'前提条件'!$B$12,(A9-1)*12+1,A9*12,0)) | N9: =K9+L9 | O9: =IF(A9<=22,'前提条件'!$B$33*'前提条件'!$B$34,0) | P9: =K9+M9-O9 | Q9: =-MAX(0,P9*'前提条件'!$B$35) | R9: =N9+Q9 | S9: =S8+R9
A10: 7 | B10: ='前提条件'!$B$19*(1-'前提条件'!$B$22)^(A10-1) | C10: =-B10*IF(A10>=16,'前提条件'!$B$21,'前提条件'!$B$20) | D10: =B10+C10 | E10: =-D10*'前提条件'!$B$25 | F10: =-'前提条件'!$B$26 | G10: =-'前提条件'!$B$27 | H10: =-'前提条件'!$B$28 | I10: =-IF(A10='前提条件'!$B$29,'前提条件'!$C$29,0)-IF(A10='前提条件'!$B$30,'前提条件'!$C$30,0) | J10: =SUM(E10:I10) | K10: =D10+J10 | L10: =-IF(A10<='前提条件'!$B$14,'前提条件'!$B$15,0) | M10: =IF(OR(A10>'前提条件'!$B$14,'前提条件'!$B$12<=0,'前提条件'!$B$13<=0),0,CUMIPMT('前提条件'!$B$13/12,'前提条件'!$B$14*12,'前提条件'!$B$12,(A10-1)*12+1,A10*12,0)) | N10: =K10+L10 | O10: =IF(A10<=22,'前提条件'!$B$33*'前提条件'!$B$34,0) | P10: =K10+M10-O10 | Q10: =-MAX(0,P10*'前提条件'!$B$35) | R10: =N10+Q10 | S10: =S9+R10
A11: 8 | B11: ='前提条件'!$B$19*(1-'前提条件'!$B$22)^(A11-1) | C11: =-B11*IF(A11>=16,'前提条件'!$B$21,'前提条件'!$B$20) | D11: =B11+C11 | E11: =-D11*'前提条件'!$B$25 | F11: =-'前提条件'!$B$26 | G11: =-'前提条件'!$B$27 | H11: =-'前提条件'!$B$28 | I11: =-IF(A11='前提条件'!$B$29,'前提条件'!$C$29,0)-IF(A11='前提条件'!$B$30,'前提条件'!$C$30,0) | J11: =SUM(E11:I11) | K11: =D11+J11 | L11: =-IF(A11<='前提条件'!$B$14,'前提条件'!$B$15,0) | M11: =IF(OR(A11>'前提条件'!$B$14,'前提条件'!$B$12<=0,'前提条件'!$B$13<=0),0,CUMIPMT('前提条件'!$B$13/12,'前提条件'!$B$14*12,'前提条件'!$B$12,(A11-1)*12+1,A11*12,0)) | N11: =K11+L11 | O11: =IF(A11<=22,'前提条件'!$B$33*'前提条件'!$B$34,0) | P11: =K11+M11-O11 | Q11: =-MAX(0,P11*'前提条件'!$B$35) | R11: =N11+Q11 | S11: =S10+R11
A12: 9 | B12: ='前提条件'!$B$19*(1-'前提条件'!$B$22)^(A12-1) | C12: =-B12*IF(A12>=16,'前提条件'!$B$21,'前提条件'!$B$20) | D12: =B12+C12 | E12: =-D12*'前提条件'!$B$25 | F12: =-'前提条件'!$B$26 | G12: =-'前提条件'!$B$27 | H12: =-'前提条件'!$B$28 | I12: =-IF(A12='前提条件'!$B$29,'前提条件'!$C$29,0)-IF(A12='前提条件'!$B$30,'前提条件'!$C$30,0) | J12: =SUM(E12:I12) | K12: =D12+J12 | L12: =-IF(A12<='前提条件'!$B$14,'前提条件'!$B$15,0) | M12: =IF(OR(A12>'前提条件'!$B$14,'前提条件'!$B$12<=0,'前提条件'!$B$13<=0),0,CUMIPMT('前提条件'!$B$13/12,'前提条件'!$B$14*12,'前提条件'!$B$12,(A12-1)*12+1,A12*12,0)) | N12: =K12+L12 | O12: =IF(A12<=22,'前提条件'!$B$33*'前提条件'!$B$34,0) | P12: =K12+M12-O12 | Q12: =-MAX(0,P12*'前提条件'!$B$35) | R12: =N12+Q12 | S12: =S11+R12
A13: 10 | B13: ='前提条件'!$B$19*(1-'前提条件'!$B$22)^(A13-1) | C13: =-B13*IF(A13>=16,'前提条件'!$B$21,'前提条件'!$B$20) | D13: =B13+C13 | E13: =-D13*'前提条件'!$B$25 | F13: =-'前提条件'!$B$26 | G13: =-'前提条件'!$B$27 | H13: =-'前提条件'!$B$28 | I13: =-IF(A13='前提条件'!$B$29,'前提条件'!$C$29,0)-IF(A13='前提条件'!$B$30,'前提条件'!$C$30,0) | J13: =SUM(E13:I13) | K13: =D13+J13 | L13: =-IF(A13<='前提条件'!$B$14,'前提条件'!$B$15,0) | M13: =IF(OR(A13>'前提条件'!$B$14,'前提条件'!$B$12<=0,'前提条件'!$B$13<=0),0,CUMIPMT('前提条件'!$B$13/12,'前提条件'!$B$14*12,'前提条件'!$B$12,(A13-1)*12+1,A13*12,0)) | N13: =K13+L13 | O13: =IF(A13<=22,'前提条件'!$B$33*'前提条件'!$B$34,0) | P13: =K13+M13-O13 | Q13: =-MAX(0,P13*'前提条件'!$B$35) | R13: =N13+Q13 | S13: =S12+R13
A14: 11 | B14: ='前提条件'!$B$19*(1-'前提条件'!$B$22)^(A14-1) | C14: =-B14*IF(A14>=16,'前提条件'!$B$21,'前提条件'!$B$20) | D14: =B14+C14 | E14: =-D14*'前提条件'!$B$25 | F14: =-'前提条件'!$B$26 | G14: =-'前提条件'!$B$27 | H14: =-'前提条件'!$B$28 | I14: =-IF(A14='前提条件'!$B$29,'前提条件'!$C$29,0)-IF(A14='前提条件'!$B$30,'前提条件'!$C$30,0) | J14: =SUM(E14:I14) | K14: =D14+J14 | L14: =-IF(A14<='前提条件'!$B$14,'前提条件'!$B$15,0) | M14: =IF(OR(A14>'前提条件'!$B$14,'前提条件'!$B$12<=0,'前提条件'!$B$13<=0),0,CUMIPMT('前提条件'!$B$13/12,'前提条件'!$B$14*12,'前提条件'!$B$12,(A14-1)*12+1,A14*12,0)) | N14: =K14+L14 | O14: =IF(A14<=22,'前提条件'!$B$33*'前提条件'!$B$34,0) | P14: =K14+M14-O14 | Q14: =-MAX(0,P14*'前提条件'!$B$35) | R14: =N14+Q14 | S14: =S13+R14
A15: 12 | B15: ='前提条件'!$B$19*(1-'前提条件'!$B$22)^(A15-1) | C15: =-B15*IF(A15>=16,'前提条件'!$B$21,'前提条件'!$B$20) | D15: =B15+C15 | E15: =-D15*'前提条件'!$B$25 | F15: =-'前提条件'!$B$26 | G15: =-'前提条件'!$B$27 | H15: =-'前提条件'!$B$28 | I15: =-IF(A15='前提条件'!$B$29,'前提条件'!$C$29,0)-IF(A15='前提条件'!$B$30,'前提条件'!$C$30,0) | J15: =SUM(E15:I15) | K15: =D15+J15 | L15: =-IF(A15<='前提条件'!$B$14,'前提条件'!$B$15,0) | M15: =IF(OR(A15>'前提条件'!$B$14,'前提条件'!$B$12<=0,'前提条件'!$B$13<=0),0,CUMIPMT('前提条件'!$B$13/12,'前提条件'!$B$14*12,'前提条件'!$B$12,(A15-1)*12+1,A15*12,0)) | N15: =K15+L15 | O15: =IF(A15<=22,'前提条件'!$B$33*'前提条件'!$B$34,0) | P15: =K15+M15-O15 | Q15: =-MAX(0,P15*'前提条件'!$B$35) | R15: =N15+Q15 | S15: =S14+R15
A16: 13 | B16: ='前提条件'!$B$19*(1-'前提条件'!$B$22)^(A16-1) | C16: =-B16*IF(A16>=16,'前提条件'!$B$21,'前提条件'!$B$20) | D16: =B16+C16 | E16: =-D16*'前提条件'!$B$25 | F16: =-'前提条件'!$B$26 | G16: =-'前提条件'!$B$27 | H16: =-'前提条件'!$B$28 | I16: =-IF(A16='前提条件'!$B$29,'前提条件'!$C$29,0)-IF(A16='前提条件'!$B$30,'前提条件'!$C$30,0) | J16: =SUM(E16:I16) | K16: =D16+J16 | L16: =-IF(A16<='前提条件'!$B$14,'前提条件'!$B$15,0) | M16: =IF(OR(A16>'前提条件'!$B$14,'前提条件'!$B$12<=0,'前提条件'!$B$13<=0),0,CUMIPMT('前提条件'!$B$13/12,'前提条件'!$B$14*12,'前提条件'!$B$12,(A16-1)*12+1,A16*12,0)) | N16: =K16+L16 | O16: =IF(A16<=22,'前提条件'!$B$33*'前提条件'!$B$34,0) | P16: =K16+M16-O16 | Q16: =-MAX(0,P16*'前提条件'!$B$35) | R16: =N16+Q16 | S16: =S15+R16
... A33: 30 | B33: ='前提条件'!$B$19*(1-'前提条件'!$B$22)^(A33-1) | C33: =-B33*IF(A33>=16,'前提条件'!$B$21,'前提条件'!$B$20) | D33: =B33+C33 | E33: =-D33*'前提条件'!$B$25 | F33: =-'前提条件'!$B$26 | G33: =-'前提条件'!$B$27 | H33: =-'前提条件'!$B$28 | I33: =-IF(A33='前提条件'!$B$29,'前提条件'!$C$29,0)-IF(A33='前提条件'!$B$30,'前提条件'!$C$30,0) | J33: =SUM(E33:I33) | K33: =D33+J33 | L33: =-IF(A33<='前提条件'!$B$14,'前提条件'!$B$15,0) | M33: =IF(OR(A33>'前提条件'!$B$14,'前提条件'!$B$12<=0,'前提条件'!$B$13<=0),0,CUMIPMT('前提条件'!$B$13/12,'前提条件'!$B$14*12,'前提条件'!$B$12,(A33-1)*12+1,A33*12,0)) | N33: =K33+L33 | O33: =IF(A33<=22,'前提条件'!$B$33*'前提条件'!$B$34,0) | P33: =K33+M33-O33 | Q33: =-MAX(0,P33*'前提条件'!$B$35) | R33: =N33+Q33 | S33: =S32+R33
A34: 合計 | B34: =SUM(B4:B33) | C34: =SUM(C4:C33) | D34: =SUM(D4:D33) | E34: =SUM(E4:E33) | F34: =SUM(F4:F33) | G34: =SUM(G4:G33) | H34: =SUM(H4:H33) | I34: =SUM(I4:I33) | ... O34: =SUM(O4:O33) | Q34: =SUM(Q4:Q33) | R34: =SUM(R4:R33) | S34: =S33
A36: ※ 税金(概算)は不動産所得×適用税率の簡易計算です(青色申告特別控除・損益通算等は未反映)。正式な税額は税理士試算によります。

Sheet サマリー
A1: 投資サマリー・金利上昇シナリオ比較
A3: ■ 主要指標
A4: 総事業費 | B4: ='前提条件'!B8
A5: 自己資金 / 借入額 | B5: ='前提条件'!B11 | C5: ='前提条件'!B12 | E5: 隣は借入額
A6: 表面利回り(満室時家賃 ÷ 総事業費) | B6: ='前提条件'!B19/'前提条件'!B8 | E6: 土地は自己所有のため建物投資に対する利回り
A7: 実質利回り(1年目NOI ÷ 総事業費) | B7: =収支計画30年!K4/'前提条件'!B8 | E7: 運営費控除後
A8: DSCR(1年目NOI ÷ 年間返済額) | B8: =IF('前提条件'!B15=0,"借入なし",収支計画30年!K4/'前提条件'!B15) | E8: 1.2以上が金融機関の目安
A9: 1年目 税引後キャッシュフロー | B9: =収支計画30年!R4
A10: 返済終了後(26年目)の年間手残り | B10: =収支計画30年!R29 | E10: 無借金の収益資産になります
A11: 30年累計 税引後キャッシュフロー | B11: =収支計画30年!S33
A12: 30年累計 − 自己資金(純増額) | B12: =収支計画30年!S33-'前提条件'!B11 | E12: 投下自己資金を差し引いた実質手取り
A14: ■ 金利上昇シナリオ(1年目ベース)
B15: 現行金利 | C15: +1.0% | D15: +2.0%
A16: 適用金利 | B16: ='前提条件'!B13 | C16: ='前提条件'!B13+0.01 | D16: ='前提条件'!B13+0.02
A17: 年間返済額 | B17: =IF('前提条件'!B12<=0,0,PMT(('前提条件'!B13+0)/12,'前提条件'!B14*12,-'前提条件'!B12)*12) | C17: =IF('前提条件'!B12<=0,0,PMT(('前提条件'!B13+0.01)/12,'前提条件'!B14*12,-'前提条件'!B12)*12) | D17: =IF('前提条件'!B12<=0,0,PMT(('前提条件'!B13+0.02)/12,'前提条件'!B14*12,-'前提条件'!B12)*12)
A18: 1年目 税引前キャッシュフロー | B18: =収支計画30年!K4-B17 | C18: =収支計画30年!K4-C17 | D18: =収支計画30年!K4-D17 | E18: 金利が2%上がっても赤字にならないかを確認
A20: ※ 本書は一定の前提に基づく概算シミュレーションであり、将来の収益を保証するものではありません。
A21: ※ 大規模修繕年は一時的にキャッシュフローがマイナスになります(収支計画30年シート参照)。
