Workbook

Sheet 設定
A1: Aether 見積・実行予算システム（試作版）
A2: 作成日 | B2: 46165
A3: 消費税率 | B3: 0.1 | C3: お客様見積書の税込計算に使用
A4: 目標粗利率 | B4: 0.3 | C4: 社内実行予算書の判定に使用
A5: 最低粗利率（警告） | B5: 0.25 | C5: 下回ると警告表示
A6: 会社名 | B6: 株式会社Aether
A7: 代表者 | B7: 伊藤 雄一
A8: 備考 | B8: 入力シートへ一度入力すると、お客様見積書・社内実行予算書へ反映されます。
A9: 見積有効期限（日数） | B9: 30 | C9: 作成日からの有効日数
A10: お支払条件 | B10: 着手金50％、完工時残金50％ | C10: お客様見積書に表示
A11: 振込先 | B11: （銀行名・支店名・口座番号を記入） | C11: お客様見積書に表示
A12: 特記事項 | B12: 別途、現場状況により追加費用が発生する場合があります。 | C12: お客様見積書に表示

Sheet 入力シート
A1: No | B1: 部屋・工区 | C1: カテゴリ | D1: 工事項目 | E1: 数量 | F1: 単位 | G1: お客様単価 | H1: お客様手入力金額 | I1: お客様金額 | J1: 実行数量 | K1: 実行単位 | L1: 実行単価 | M1: 実行手入力金額 | N1: 実行金額 | O1: 粗利額 | P1: 粗利率 | Q1: 定価・掛率・人工費 | R1: 商品名・品番・メーカー | S1: 表示 | T1: 備考
A2: 1 | B2: 玄関ホール、廊下、階段室吹抜 | C2: 材料 | D2: 床 上り框 | E2: 1 | F2: 本 | G2: 8600 | I2: =IF($A2="","",IF($S2<>"表示",0,IF($H2>0,$H2,IFERROR($E2*$G2,0)))) | J2: 1 | K2: 本 | L2: 5320 | N2: =IF($A2="","",IF($S2<>"表示",0,IF($M2>0,$M2,IFERROR($J2*$L2,0)))) | O2: =IF($A2="","",$I2-$N2) | P2: =IF($A2="","",IFERROR($O2/$I2,0)) | Q2: 定価15,200円/本（2,000㎜）×35％ | R2: ノダ リフォーム上り框 7㎜厚 | S2: 表示
A3: 2 | B3: 玄関ホール、廊下、階段室吹抜 | C3: 材料 | D3: 床 フローリング | E3: 2 | F3: 梱 | G3: 8000 | I3: =IF($A3="","",IF($S3<>"表示",0,IF($H3>0,$H3,IFERROR($E3*$G3,0)))) | J3: 2 | K3: 梱 | L3: 4550 | N3: =IF($A3="","",IF($S3<>"表示",0,IF($M3>0,$M3,IFERROR($J3*$L3,0)))) | O3: =IF($A3="","",$I3-$N3) | P3: =IF($A3="","",IFERROR($O3/$I3,0)) | Q3: 定価13,000円/梱（3.3㎡）×35％ | R3: ノダ ウォークフィット6 6.3㎜厚 | S3: 表示
A4: 3 | B4: 玄関ホール、廊下、階段室吹抜 | C4: 材料 | D4: 巾木 | E4: 2 | F4: 本 | G4: 900 | I4: =IF($A4="","",IF($S4<>"表示",0,IF($H4>0,$H4,IFERROR($E4*$G4,0)))) | J4: 2 | K4: 本 | L4: 735 | N4: =IF($A4="","",IF($S4<>"表示",0,IF($M4>0,$M4,IFERROR($J4*$L4,0)))) | O4: =IF($A4="","",$I4-$N4) | P4: =IF($A4="","",IFERROR($O4/$I4,0)) | Q4: 定価2,100円/本×35％ | R4: ノダ 巾木C 7×60×3,950㎜（3本入） | S4: 表示
A5: 4 | B5: 玄関ホール、廊下、階段室吹抜 | C5: 材料 | D5: リフォーム階段（直14段）踏板 | E5: 13 | F5: 枚 | G5: 1400 | I5: =IF($A5="","",IF($S5<>"表示",0,IF($H5>0,$H5,IFERROR($E5*$G5,0)))) | J5: 13 | K5: 枚 | L5: 1330 | N5: =IF($A5="","",IF($S5<>"表示",0,IF($M5>0,$M5,IFERROR($J5*$L5,0)))) | O5: =IF($A5="","",$I5-$N5) | P5: =IF($A5="","",IFERROR($O5/$I5,0)) | Q5: 定価3,800円×35％ | R5: ノダ リフォーム階段 | S5: 表示
A6: 5 | B6: 玄関ホール、廊下、階段室吹抜 | C6: 材料 | D6: 〃 蹴込板 | E6: 14 | F6: 枚 | G6: 900 | I6: =IF($A6="","",IF($S6<>"表示",0,IF($H6>0,$H6,IFERROR($E6*$G6,0)))) | J6: 14 | K6: 枚 | L6: 315 | N6: =IF($A6="","",IF($S6<>"表示",0,IF($M6>0,$M6,IFERROR($J6*$L6,0)))) | O6: =IF($A6="","",$I6-$N6) | P6: =IF($A6="","",IFERROR($O6/$I6,0)) | Q6: 定価900円×35％ | R6: 〃 〃 | S6: 表示
A7: 6 | B7: 玄関ホール、廊下、階段室吹抜 | C7: 材料 | D7: 〃 段鼻部材 | E7: 13 | F7: 本 | G7: 2700 | I7: =IF($A7="","",IF($S7<>"表示",0,IF($H7>0,$H7,IFERROR($E7*$G7,0)))) | J7: 13 | K7: 本 | L7: 630 | N7: =IF($A7="","",IF($S7<>"表示",0,IF($M7>0,$M7,IFERROR($J7*$L7,0)))) | O7: =IF($A7="","",$I7-$N7) | P7: =IF($A7="","",IFERROR($O7/$I7,0)) | Q7: 定価1,800円×35％ | R7: 〃 〃 | S7: 表示
A8: 7 | B8: 玄関ホール、廊下、階段室吹抜 | C8: 材料 | D8: 〃 上段框用段鼻部材 | E8: 1 | F8: 本 | G8: 3000 | I8: =IF($A8="","",IF($S8<>"表示",0,IF($H8>0,$H8,IFERROR($E8*$G8,0)))) | J8: 1 | K8: 本 | L8: 630 | N8: =IF($A8="","",IF($S8<>"表示",0,IF($M8>0,$M8,IFERROR($J8*$L8,0)))) | O8: =IF($A8="","",$I8-$N8) | P8: =IF($A8="","",IFERROR($O8/$I8,0)) | Q8: 定価1,800円×35％ | R8: 〃 〃 | S8: 表示
A9: 8 | B9: 玄関ホール、廊下、階段室吹抜 | C9: 材料 | D9: 玄関収納 W120×H226cm 床置 | E9: 1 | F9: セット | G9: 66100 | I9: =IF($A9="","",IF($S9<>"表示",0,IF($H9>0,$H9,IFERROR($E9*$G9,0)))) | J9: 1 | K9: セット | L9: 53165 | N9: =IF($A9="","",IF($S9<>"表示",0,IF($M9>0,$M9,IFERROR($J9*$L9,0)))) | O9: =IF($A9="","",$I9-$N9) | P9: =IF($A9="","",IFERROR($O9/$I9,0)) | Q9: 定価151,900円×35％ | R9: ノダ 玄関収納コの字フラット | S9: 表示
A10: 9 | B10: 玄関ホール、廊下、階段室吹抜 | C10: 材料 | D10: 取替用玄関ドア（片袖） | E10: 1 | F10: セット | G10: 165700 | I10: =IF($A10="","",IF($S10<>"表示",0,IF($H10>0,$H10,IFERROR($E10*$G10,0)))) | J10: 1 | K10: セット | L10: 114100 | N10: =IF($A10="","",IF($S10<>"表示",0,IF($M10>0,$M10,IFERROR($J10*$L10,0)))) | O10: =IF($A10="","",$I10-$N10) | P10: =IF($A10="","",IFERROR($O10/$I10,0)) | Q10: 定価326,000円×35％ | R10: LIXIL リシェント アルミ仕様 | S10: 表示
A11: 10 | B11: 玄関ホール、廊下、階段室吹抜 | C11: 材料 | D11: 袖部ランマ袖部ガラス | E11: 1 | F11: 式 | H11: 6200 | I11: =IF($A11="","",IF($S11<>"表示",0,IF($H11>0,$H11,IFERROR($E11*$G11,0)))) | J11: 1 | K11: 式 | M11: 4650 | N11: =IF($A11="","",IF($S11<>"表示",0,IF($M11>0,$M11,IFERROR($J11*$L11,0)))) | O11: =IF($A11="","",$I11-$N11) | P11: =IF($A11="","",IFERROR($O11/$I11,0)) | R11: 5㎜ガラス | S11: 表示
A12: 11 | B12: 玄関ホール、廊下、階段室吹抜 | C12: 材料 | D12: 木枠塗装剤 | E12: 1 | F12: 式 | H12: 3200 | I12: =IF($A12="","",IF($S12<>"表示",0,IF($H12>0,$H12,IFERROR($E12*$G12,0)))) | J12: 1 | K12: 式 | M12: 2400 | N12: =IF($A12="","",IF($S12<>"表示",0,IF($M12>0,$M12,IFERROR($J12*$L12,0)))) | O12: =IF($A12="","",$I12-$N12) | P12: =IF($A12="","",IFERROR($O12/$I12,0)) | S12: 表示
A13: 12 | B13: 玄関ホール、廊下、階段室吹抜 | C13: 施工 | D13: 床 上り框取付 | E13: 1 | F13: 式 | H13: 4200 | I13: =IF($A13="","",IF($S13<>"表示",0,IF($H13>0,$H13,IFERROR($E13*$G13,0)))) | J13: 1 | K13: 式 | M13: 3000 | N13: =IF($A13="","",IF($S13<>"表示",0,IF($M13>0,$M13,IFERROR($J13*$L13,0)))) | O13: =IF($A13="","",$I13-$N13) | P13: =IF($A13="","",IFERROR($O13/$I13,0)) | S13: 表示
A14: 13 | B14: 玄関ホール、廊下、階段室吹抜 | C14: 施工 | D14: 床 フローリング重ね貼り | E14: 5.2 | F14: ㎡ | G14: 2140 | I14: =IF($A14="","",IF($S14<>"表示",0,IF($H14>0,$H14,IFERROR($E14*$G14,0)))) | J14: 5.2 | K14: ㎡ | L14: 1500 | N14: =IF($A14="","",IF($S14<>"表示",0,IF($M14>0,$M14,IFERROR($J14*$L14,0)))) | O14: =IF($A14="","",$I14-$N14) | P14: =IF($A14="","",IFERROR($O14/$I14,0)) | S14: 表示
A15: 14 | B15: 玄関ホール、廊下、階段室吹抜 | C15: 施工 | D15: 巾木取替え | E15: 6.4 | F15: ｍ | G15: 1140 | I15: =IF($A15="","",IF($S15<>"表示",0,IF($H15>0,$H15,IFERROR($E15*$G15,0)))) | J15: 6.4 | K15: m | L15: 800 | N15: =IF($A15="","",IF($S15<>"表示",0,IF($M15>0,$M15,IFERROR($J15*$L15,0)))) | O15: =IF($A15="","",$I15-$N15) | P15: =IF($A15="","",IFERROR($O15/$I15,0)) | S15: 表示
A16: 15 | B16: 玄関ホール、廊下、階段室吹抜 | C16: 施工 | D16: リフォーム階段（直14段）重ね貼り | E16: 1 | F16: 式 | H16: 28500 | I16: =IF($A16="","",IF($S16<>"表示",0,IF($H16>0,$H16,IFERROR($E16*$G16,0)))) | J16: 1 | K16: 式 | M16: 20000 | N16: =IF($A16="","",IF($S16<>"表示",0,IF($M16>0,$M16,IFERROR($J16*$L16,0)))) | O16: =IF($A16="","",$I16-$N16) | P16: =IF($A16="","",IFERROR($O16/$I16,0)) | Q16: 1人役 | S16: 表示
A17: 16 | B17: 玄関ホール、廊下、階段室吹抜 | C17: 施工 | D17: 既存玄関ドア撤去 | E17: 1 | F17: 式 | H17: 7100 | I17: =IF($A17="","",IF($S17<>"表示",0,IF($H17>0,$H17,IFERROR($E17*$G17,0)))) | J17: 1 | K17: 式 | M17: 5000 | N17: =IF($A17="","",IF($S17<>"表示",0,IF($M17>0,$M17,IFERROR($J17*$L17,0)))) | O17: =IF($A17="","",$I17-$N17) | P17: =IF($A17="","",IFERROR($O17/$I17,0)) | S17: 表示
A18: 17 | B18: 玄関ホール、廊下、階段室吹抜 | C18: 施工 | D18: 玄関ドア（リフォームドア）取替え | E18: 1 | F18: 式 | H18: 28500 | I18: =IF($A18="","",IF($S18<>"表示",0,IF($H18>0,$H18,IFERROR($E18*$G18,0)))) | J18: 1 | K18: 式 | M18: 20000 | N18: =IF($A18="","",IF($S18<>"表示",0,IF($M18>0,$M18,IFERROR($J18*$L18,0)))) | O18: =IF($A18="","",$I18-$N18) | P18: =IF($A18="","",IFERROR($O18/$I18,0)) | Q18: 1人役 | S18: 表示
A19: 18 | B19: 玄関ホール、廊下、階段室吹抜 | C19: 施工 | D19: 玄関収納取替え | E19: 1 | F19: 式 | H19: 11400 | I19: =IF($A19="","",IF($S19<>"表示",0,IF($H19>0,$H19,IFERROR($E19*$G19,0)))) | J19: 1 | K19: 式 | M19: 8000 | N19: =IF($A19="","",IF($S19<>"表示",0,IF($M19>0,$M19,IFERROR($J19*$L19,0)))) | O19: =IF($A19="","",$I19-$N19) | P19: =IF($A19="","",IFERROR($O19/$I19,0)) | Q19: 1/3人役 | S19: 表示
A20: 19 | B20: 玄関ホール、廊下、階段室吹抜 | C20: 施工 | D20: 天井 ビニールクロス貼替え | E20: 7.3 | F20: ㎡ | G20: 1140 | I20: =IF($A20="","",IF($S20<>"表示",0,IF($H20>0,$H20,IFERROR($E20*$G20,0)))) | J20: 7.3 | K20: ㎡ | L20: 650 | N20: =IF($A20="","",IF($S20<>"表示",0,IF($M20>0,$M20,IFERROR($J20*$L20,0)))) | O20: =IF($A20="","",$I20-$N20) | P20: =IF($A20="","",IFERROR($O20/$I20,0)) | Q20: 材工共 | R20: 量産品 SP | S20: 表示
A21: 20 | B21: 玄関ホール、廊下、階段室吹抜 | C21: 施工 | D21: 壁 〃 | E21: 50 | F21: ㎡ | G21: 1140 | I21: =IF($A21="","",IF($S21<>"表示",0,IF($H21>0,$H21,IFERROR($E21*$G21,0)))) | J21: 50 | K21: ㎡ | L21: 650 | N21: =IF($A21="","",IF($S21<>"表示",0,IF($M21>0,$M21,IFERROR($J21*$L21,0)))) | O21: =IF($A21="","",$I21-$N21) | P21: =IF($A21="","",IFERROR($O21/$I21,0)) | Q21: 材工共 | R21: 量産品 SP | S21: 表示
A22: 21 | B22: 玄関ホール、廊下、階段室吹抜 | C22: 施工 | D22: 木枠塗装 | E22: 1 | F22: 式 | H22: 11400 | I22: =IF($A22="","",IF($S22<>"表示",0,IF($H22>0,$H22,IFERROR($E22*$G22,0)))) | J22: 1 | K22: 式 | M22: 8000 | N22: =IF($A22="","",IF($S22<>"表示",0,IF($M22>0,$M22,IFERROR($J22*$L22,0)))) | O22: =IF($A22="","",$I22-$N22) | P22: =IF($A22="","",IFERROR($O22/$I22,0)) | Q22: 1/3人役 | S22: 表示
A23: 22 | B23: 玄関ホール、廊下、階段室吹抜 | C23: 施工 | D23: プレート取替え | E23: 3 | F23: セット | G23: 850 | I23: =IF($A23="","",IF($S23<>"表示",0,IF($H23>0,$H23,IFERROR($E23*$G23,0)))) | J23: 3 | K23: セット | L23: 600 | N23: =IF($A23="","",IF($S23<>"表示",0,IF($M23>0,$M23,IFERROR($J23*$L23,0)))) | O23: =IF($A23="","",$I23-$N23) | P23: =IF($A23="","",IFERROR($O23/$I23,0)) | Q23: 材工共 | S23: 表示
A24: 23 | B24: LDK | C24: 材料 | D24: 床 フローリング | E24: 7 | F24: 梱 | G24: 8000 | I24: =IF($A24="","",IF($S24<>"表示",0,IF($H24>0,$H24,IFERROR($E24*$G24,0)))) | J24: 7 | K24: 梱 | L24: 4550 | N24: =IF($A24="","",IF($S24<>"表示",0,IF($M24>0,$M24,IFERROR($J24*$L24,0)))) | O24: =IF($A24="","",$I24-$N24) | P24: =IF($A24="","",IFERROR($O24/$I24,0)) | Q24: 定価13,000円/梱（3.3㎡）×35％ | R24: ノダ ウォークフィット6 6.3㎜厚 | S24: 表示
A25: 24 | B25: LDK | C25: 材料 | D25: 巾木 | E25: 4 | F25: 本 | G25: 900 | I25: =IF($A25="","",IF($S25<>"表示",0,IF($H25>0,$H25,IFERROR($E25*$G25,0)))) | J25: 4 | K25: 本 | L25: 735 | N25: =IF($A25="","",IF($S25<>"表示",0,IF($M25>0,$M25,IFERROR($J25*$L25,0)))) | O25: =IF($A25="","",$I25-$N25) | P25: =IF($A25="","",IFERROR($O25/$I25,0)) | Q25: 定価2,100円/本×35％ | R25: ノダ 巾木C 7×60×3,950㎜（3本入） ☆ | S25: 表示
A26: 25 | B26: LDK | C26: 材料 | D26: リビング片開き戸（ドアのみガラス入） | E26: 1 | F26: セット | G26: 57300 | I26: =IF($A26="","",IF($S26<>"表示",0,IF($H26>0,$H26,IFERROR($E26*$G26,0)))) | J26: 1 | K26: セット | L26: 43000 | N26: =IF($A26="","",IF($S26<>"表示",0,IF($M26>0,$M26,IFERROR($J26*$L26,0)))) | O26: =IF($A26="","",$I26-$N26) | P26: =IF($A26="","",IFERROR($O26/$I26,0)) | R26: 別注 フラッシュ框ドア（ガラス入）金物含む | S26: 表示
A27: 26 | B27: LDK | C27: 材料 | D27: 〃 （ドアのみ） | E27: 1 | F27: セット | G27: 24000 | I27: =IF($A27="","",IF($S27<>"表示",0,IF($H27>0,$H27,IFERROR($E27*$G27,0)))) | J27: 1 | K27: セット | L27: 18000 | N27: =IF($A27="","",IF($S27<>"表示",0,IF($M27>0,$M27,IFERROR($J27*$L27,0)))) | O27: =IF($A27="","",$I27-$N27) | P27: =IF($A27="","",IFERROR($O27/$I27,0)) | R27: 別注 プリント貼り フラッシュドア 金物含む | S27: 表示
A28: 27 | B28: LDK | C28: 材料 | D28: システムキッチン I型2550 | E28: 1 | F28: セット | G28: 261600 | I28: =IF($A28="","",IF($S28<>"表示",0,IF($H28>0,$H28,IFERROR($E28*$G28,0)))) | J28: 1 | K28: セット | L28: 196230 | N28: =IF($A28="","",IF($S28<>"表示",0,IF($M28>0,$M28,IFERROR($J28*$L28,0)))) | O28: =IF($A28="","",$I28-$N28) | P28: =IF($A28="","",IFERROR($O28/$I28,0)) | Q28: 定価633,000円×31％ | R28: トクラス Bb スライドタイプ 扉E/C ☆ | S28: 表示
A29: 28 | B29: LDK | C29: 材料 | D29: キッチンパネル | E29: 2 | F29: 枚 | G29: 12600 | I29: =IF($A29="","",IF($S29<>"表示",0,IF($H29>0,$H29,IFERROR($E29*$G29,0)))) | J29: 2 | K29: 枚 | L29: 9464 | N29: =IF($A29="","",IF($S29<>"表示",0,IF($M29>0,$M29,IFERROR($J29*$L29,0)))) | O29: =IF($A29="","",$I29-$N29) | P29: =IF($A29="","",IFERROR($O29/$I29,0)) | Q29: 定価18,200円/枚×52％マ | R29: アイカ工業 セラール 3×8 ☆ | S29: 表示
A30: 29 | B30: LDK | C30: 材料 | D30: 〃 施工部材 | E30: 1 | F30: セット | G30: 6500 | I30: =IF($A30="","",IF($S30<>"表示",0,IF($H30>0,$H30,IFERROR($E30*$G30,0)))) | J30: 1 | K30: セット | L30: 4929 | N30: =IF($A30="","",IF($S30<>"表示",0,IF($M30>0,$M30,IFERROR($J30*$L30,0)))) | O30: =IF($A30="","",$I30-$N30) | P30: =IF($A30="","",IFERROR($O30/$I30,0)) | Q30: 定価9,300円×53％ | R30: 専用接着剤 見切りジョイナー（2本） ☆ | S30: 表示
A31: 30 | B31: LDK | C31: 材料 | D31: 〃 下地材 | E31: 1 | F31: 式 | H31: 13300 | I31: =IF($A31="","",IF($S31<>"表示",0,IF($H31>0,$H31,IFERROR($E31*$G31,0)))) | J31: 1 | K31: 式 | M31: 10000 | N31: =IF($A31="","",IF($S31<>"表示",0,IF($M31>0,$M31,IFERROR($J31*$L31,0)))) | O31: =IF($A31="","",$I31-$N31) | P31: =IF($A31="","",IFERROR($O31/$I31,0)) | R31: 合板及び銅縁材他 | S31: 表示
A32: 31 | B32: LDK | C32: 材料 | D32: 木枠塗装剤ウ | E32: 1 | F32: 式 | H32: 10600 | I32: =IF($A32="","",IF($S32<>"表示",0,IF($H32>0,$H32,IFERROR($E32*$G32,0)))) | J32: 1 | K32: 式 | M32: 8000 | N32: =IF($A32="","",IF($S32<>"表示",0,IF($M32>0,$M32,IFERROR($J32*$L32,0)))) | O32: =IF($A32="","",$I32-$N32) | P32: =IF($A32="","",IFERROR($O32/$I32,0)) | S32: 表示
A33: 32 | B33: LDK | C33: 施工 | D33: 床 フローリング重ね貼り | E33: 23.2 | F33: ㎡ | G33: 2140 | I33: =IF($A33="","",IF($S33<>"表示",0,IF($H33>0,$H33,IFERROR($E33*$G33,0)))) | J33: 23.2 | K33: ㎡ | L33: 1500 | N33: =IF($A33="","",IF($S33<>"表示",0,IF($M33>0,$M33,IFERROR($J33*$L33,0)))) | O33: =IF($A33="","",$I33-$N33) | P33: =IF($A33="","",IFERROR($O33/$I33,0)) | S33: 表示
A34: 33 | B34: LDK | C34: 施工 | D34: 巾木取替え | E34: 14.8 | F34: m | G34: 850 | I34: =IF($A34="","",IF($S34<>"表示",0,IF($H34>0,$H34,IFERROR($E34*$G34,0)))) | J34: 14.8 | K34: m | L34: 600 | N34: =IF($A34="","",IF($S34<>"表示",0,IF($M34>0,$M34,IFERROR($J34*$L34,0)))) | O34: =IF($A34="","",$I34-$N34) | P34: =IF($A34="","",IFERROR($O34/$I34,0)) | S34: 表示
A35: 34 | B35: LDK | C35: 施工 | D35: 片開き戸取替え 2ヶ所 | E35: 1 | F35: 式 | H35: 8400 | I35: =IF($A35="","",IF($S35<>"表示",0,IF($H35>0,$H35,IFERROR($E35*$G35,0)))) | J35: 1 | K35: 式 | M35: 6000 | N35: =IF($A35="","",IF($S35<>"表示",0,IF($M35>0,$M35,IFERROR($J35*$L35,0)))) | O35: =IF($A35="","",$I35-$N35) | P35: =IF($A35="","",IFERROR($O35/$I35,0)) | R35: 建付調整 | S35: 表示
A36: 35 | B36: LDK | C36: 施工 | D36: 解体工事（既存キッチン） | E36: 1 | F36: 式 | H36: 28500 | I36: =IF($A36="","",IF($S36<>"表示",0,IF($H36>0,$H36,IFERROR($E36*$G36,0)))) | J36: 1 | K36: 式 | M36: 20000 | N36: =IF($A36="","",IF($S36<>"表示",0,IF($M36>0,$M36,IFERROR($J36*$L36,0)))) | O36: =IF($A36="","",$I36-$N36) | P36: =IF($A36="","",IFERROR($O36/$I36,0)) | Q36: 1人役 | S36: 表示
A37: 36 | B37: LDK | C37: 経費 | D37: 〃 廃棄費 | E37: 1 | F37: 式 | H37: 21400 | I37: =IF($A37="","",IF($S37<>"表示",0,IF($H37>0,$H37,IFERROR($E37*$G37,0)))) | J37: 1 | K37: 式 | M37: 15000 | N37: =IF($A37="","",IF($S37<>"表示",0,IF($M37>0,$M37,IFERROR($J37*$L37,0)))) | O37: =IF($A37="","",$I37-$N37) | P37: =IF($A37="","",IFERROR($O37/$I37,0)) | S37: 表示
A38: 37 | B38: LDK | C38: 施工 | D38: システムキッチン取付 | E38: 1 | F38: 式 | H38: 57100 | I38: =IF($A38="","",IF($S38<>"表示",0,IF($H38>0,$H38,IFERROR($E38*$G38,0)))) | J38: 1 | K38: 式 | M38: 40000 | N38: =IF($A38="","",IF($S38<>"表示",0,IF($M38>0,$M38,IFERROR($J38*$L38,0)))) | O38: =IF($A38="","",$I38-$N38) | P38: =IF($A38="","",IFERROR($O38/$I38,0)) | Q38: 1人役 | S38: 表示
A39: 38 | B39: LDK | C39: 施工 | D39: キッチンパネル下地工事 | E39: 1 | F39: 式 | H39: 28500 | I39: =IF($A39="","",IF($S39<>"表示",0,IF($H39>0,$H39,IFERROR($E39*$G39,0)))) | J39: 1 | K39: 式 | M39: 20000 | N39: =IF($A39="","",IF($S39<>"表示",0,IF($M39>0,$M39,IFERROR($J39*$L39,0)))) | O39: =IF($A39="","",$I39-$N39) | P39: =IF($A39="","",IFERROR($O39/$I39,0)) | Q39: 1/3人役 | S39: 表示
A40: 39 | B40: LDK | C40: 施工 | D40: 〃 取付 | E40: 1 | F40: 式 | H40: 28500 | I40: =IF($A40="","",IF($S40<>"表示",0,IF($H40>0,$H40,IFERROR($E40*$G40,0)))) | J40: 1 | K40: 式 | M40: 20000 | N40: =IF($A40="","",IF($S40<>"表示",0,IF($M40>0,$M40,IFERROR($J40*$L40,0)))) | O40: =IF($A40="","",$I40-$N40) | P40: =IF($A40="","",IFERROR($O40/$I40,0)) | S40: 表示
A41: 40 | B41: LDK | C41: 施工 | D41: 給水給湯排水工事 | E41: 1 | F41: 式 | H41: 61400 | I41: =IF($A41="","",IF($S41<>"表示",0,IF($H41>0,$H41,IFERROR($E41*$G41,0)))) | J41: 1 | K41: 式 | M41: 43000 | N41: =IF($A41="","",IF($S41<>"表示",0,IF($M41>0,$M41,IFERROR($J41*$L41,0)))) | O41: =IF($A41="","",$I41-$N41) | P41: =IF($A41="","",IFERROR($O41/$I41,0)) | R41: 副資材含む | S41: 表示
A42: 41 | B42: LDK | C42: 施工 | D42: 電気工事 | E42: 1 | F42: 式 | H42: 37100 | I42: =IF($A42="","",IF($S42<>"表示",0,IF($H42>0,$H42,IFERROR($E42*$G42,0)))) | J42: 1 | K42: 式 | M42: 26000 | N42: =IF($A42="","",IF($S42<>"表示",0,IF($M42>0,$M42,IFERROR($J42*$L42,0)))) | O42: =IF($A42="","",$I42-$N42) | P42: =IF($A42="","",IFERROR($O42/$I42,0)) | R42: 〃 | S42: 表示
A43: 42 | B43: LDK | C43: 施工 | D43: 換気工事 | E43: 1 | F43: 式 | H43: 21400 | I43: =IF($A43="","",IF($S43<>"表示",0,IF($H43>0,$H43,IFERROR($E43*$G43,0)))) | J43: 1 | K43: 式 | M43: 15000 | N43: =IF($A43="","",IF($S43<>"表示",0,IF($M43>0,$M43,IFERROR($J43*$L43,0)))) | O43: =IF($A43="","",$I43-$N43) | P43: =IF($A43="","",IFERROR($O43/$I43,0)) | R43: 〃 | S43: 表示
A44: 43 | B44: LDK | C44: 施工 | D44: ガス工事 | E44: 1 | F44: 式 | H44: 22800 | I44: =IF($A44="","",IF($S44<>"表示",0,IF($H44>0,$H44,IFERROR($E44*$G44,0)))) | J44: 1 | K44: 式 | M44: 16000 | N44: =IF($A44="","",IF($S44<>"表示",0,IF($M44>0,$M44,IFERROR($J44*$L44,0)))) | O44: =IF($A44="","",$I44-$N44) | P44: =IF($A44="","",IFERROR($O44/$I44,0)) | S44: 表示
A45: 44 | B45: LDK | C45: 施工 | D45: 天井 ビニールクロス貼替え | E45: 23.2 | F45: ㎡ | G45: 1140 | I45: =IF($A45="","",IF($S45<>"表示",0,IF($H45>0,$H45,IFERROR($E45*$G45,0)))) | J45: 23.2 | K45: ㎡ | L45: 650 | N45: =IF($A45="","",IF($S45<>"表示",0,IF($M45>0,$M45,IFERROR($J45*$L45,0)))) | O45: =IF($A45="","",$I45-$N45) | P45: =IF($A45="","",IFERROR($O45/$I45,0)) | Q45: 材工共 | R45: 量産品 SP | S45: 表示
A46: 45 | B46: LDK | C46: 施工 | D46: 壁 〃 | E46: 36 | F46: ㎡ | G46: 1140 | I46: =IF($A46="","",IF($S46<>"表示",0,IF($H46>0,$H46,IFERROR($E46*$G46,0)))) | J46: 36 | K46: ㎡ | L46: 650 | N46: =IF($A46="","",IF($S46<>"表示",0,IF($M46>0,$M46,IFERROR($J46*$L46,0)))) | O46: =IF($A46="","",$I46-$N46) | P46: =IF($A46="","",IFERROR($O46/$I46,0)) | Q46: 材工共 | R46: 〃 SP | S46: 表示
A47: 46 | B47: LDK | C47: 施工 | D47: 木枠塗装 | E47: 1 | F47: 式 | H47: 11400 | I47: =IF($A47="","",IF($S47<>"表示",0,IF($H47>0,$H47,IFERROR($E47*$G47,0)))) | J47: 1 | K47: 式 | M47: 8000 | N47: =IF($A47="","",IF($S47<>"表示",0,IF($M47>0,$M47,IFERROR($J47*$L47,0)))) | O47: =IF($A47="","",$I47-$N47) | P47: =IF($A47="","",IFERROR($O47/$I47,0)) | Q47: 1/3人役 | S47: 表示
A48: 47 | B48: LDK | C48: 施工 | D48: プレート取替え | E48: 3 | F48: セット | G48: 850 | I48: =IF($A48="","",IF($S48<>"表示",0,IF($H48>0,$H48,IFERROR($E48*$G48,0)))) | J48: 3 | K48: セット | L48: 600 | N48: =IF($A48="","",IF($S48<>"表示",0,IF($M48>0,$M48,IFERROR($J48*$L48,0)))) | O48: =IF($A48="","",$I48-$N48) | P48: =IF($A48="","",IFERROR($O48/$I48,0)) | Q48: 材工共 | S48: 表示
A49: 48 | B49: 浴室 | C49: 材料 | D49: 洗面間仕切り補修材及びサッシ廻り補修材 | E49: 1 | F49: 式 | H49: 6600 | I49: =IF($A49="","",IF($S49<>"表示",0,IF($H49>0,$H49,IFERROR($E49*$G49,0)))) | J49: 1 | K49: 式 | M49: 5000 | N49: =IF($A49="","",IF($S49<>"表示",0,IF($M49>0,$M49,IFERROR($J49*$L49,0)))) | O49: =IF($A49="","",$I49-$N49) | P49: =IF($A49="","",IFERROR($O49/$I49,0)) | R49: PB及び銅縁材他 | S49: 表示
A50: 49 | B50: 浴室 | C50: 材料 | D50: 浴室入口化粧4方枠材 | E50: 1 | F50: 梱 | G50: 5700 | I50: =IF($A50="","",IF($S50<>"表示",0,IF($H50>0,$H50,IFERROR($E50*$G50,0)))) | J50: 1 | K50: 梱 | L50: 4305 | N50: =IF($A50="","",IF($S50<>"表示",0,IF($M50>0,$M50,IFERROR($J50*$L50,0)))) | O50: =IF($A50="","",$I50-$N50) | P50: =IF($A50="","",IFERROR($O50/$I50,0)) | Q50: 定価12,300円/本×35％ | R50: パル 固定枠 20×95㎜（2本入） ☆ | S50: 表示
A51: 50 | B51: 浴室 | C51: 材料 | D51: システムバス 1616（1坪）サイズ | E51: 1 | F51: セット | G51: 352900 | I51: =IF($A51="","",IF($S51<>"表示",0,IF($H51>0,$H51,IFERROR($E51*$G51,0)))) | J51: 1 | K51: セット | L51: 264693 | N51: =IF($A51="","",IF($S51<>"表示",0,IF($M51>0,$M51,IFERROR($J51*$L51,0)))) | O51: =IF($A51="","",$I51-$N51) | P51: =IF($A51="","",IFERROR($O51/$I51,0)) | Q51: 定価802,100円/本×33％ | R51: TOTO サザナ HDシリーズ Sタイプ ☆ | S51: 表示
A52: 51 | B52: 浴室 | C52: 材料 | D52: 〃 窓枠 D200 | E52: 1 | F52: セット | G52: 10700 | I52: =IF($A52="","",IF($S52<>"表示",0,IF($H52>0,$H52,IFERROR($E52*$G52,0)))) | J52: 1 | K52: セット | L52: 8085 | N52: =IF($A52="","",IF($S52<>"表示",0,IF($M52>0,$M52,IFERROR($J52*$L52,0)))) | O52: =IF($A52="","",$I52-$N52) | P52: =IF($A52="","",IFERROR($O52/$I52,0)) | Q52: 定価24,500円/本×33％ | R52: 〃 〃 フリーサイズ窓枠 ☆ | S52: 表示
A53: 52 | B53: 浴室 | C53: 材料 | D53: 土間下地材 | E53: 1 | F53: 式 | H53: 12000 | I53: =IF($A53="","",IF($S53<>"表示",0,IF($H53>0,$H53,IFERROR($E53*$G53,0)))) | J53: 1 | K53: 式 | M53: 9000 | N53: =IF($A53="","",IF($S53<>"表示",0,IF($M53>0,$M53,IFERROR($J53*$L53,0)))) | O53: =IF($A53="","",$I53-$N53) | P53: =IF($A53="","",IFERROR($O53/$I53,0)) | R53: モルタル等 | S53: 表示
A54: 53 | B54: 浴室 | C54: 材料 | D54: ガス給湯器 オートタイプ 24号 | E54: 1 | F54: セット | G54: 94600 | I54: =IF($A54="","",IF($S54<>"表示",0,IF($H54>0,$H54,IFERROR($E54*$G54,0)))) | J54: 1 | K54: セット | L54: 71000 | N54: =IF($A54="","",IF($S54<>"表示",0,IF($M54>0,$M54,IFERROR($J54*$L54,0)))) | O54: =IF($A54="","",$I54-$N54) | P54: =IF($A54="","",IFERROR($O54/$I54,0)) | Q54: 定価オープン価格 | R54: リンナイ ユッコUF 設置フリー形 シンプルリモコンセット ☆ | S54: 表示
A55: 54 | B55: 浴室 | C55: 施工 | D55: 解体工事 木工解体 | E55: 1 | F55: 式 | H55: 28500 | I55: =IF($A55="","",IF($S55<>"表示",0,IF($H55>0,$H55,IFERROR($E55*$G55,0)))) | J55: 1 | K55: 式 | M55: 20000 | N55: =IF($A55="","",IF($S55<>"表示",0,IF($M55>0,$M55,IFERROR($J55*$L55,0)))) | O55: =IF($A55="","",$I55-$N55) | P55: =IF($A55="","",IFERROR($O55/$I55,0)) | Q55: 1人役 | S55: 表示
A56: 55 | B56: 浴室 | C56: 施工 | D56: 〃 土間 | E56: 1 | F56: 式 | H56: 57100 | I56: =IF($A56="","",IF($S56<>"表示",0,IF($H56>0,$H56,IFERROR($E56*$G56,0)))) | J56: 1 | K56: 式 | M56: 40000 | N56: =IF($A56="","",IF($S56<>"表示",0,IF($M56>0,$M56,IFERROR($J56*$L56,0)))) | O56: =IF($A56="","",$I56-$N56) | P56: =IF($A56="","",IFERROR($O56/$I56,0)) | Q56: 2人役 | S56: 表示
A57: 56 | B57: 浴室 | C57: 経費 | D57: 解体材廃棄費 | E57: 1 | F57: 式 | H57: 40000 | I57: =IF($A57="","",IF($S57<>"表示",0,IF($H57>0,$H57,IFERROR($E57*$G57,0)))) | J57: 1 | K57: 式 | M57: 28000 | N57: =IF($A57="","",IF($S57<>"表示",0,IF($M57>0,$M57,IFERROR($J57*$L57,0)))) | O57: =IF($A57="","",$I57-$N57) | P57: =IF($A57="","",IFERROR($O57/$I57,0)) | R57: 1〜2t程度 | S57: 表示
A58: 57 | B58: 浴室 | C58: 施工 | D58: 木工事 間仕切補修 | E58: 1 | F58: 式 | H58: 14200 | I58: =IF($A58="","",IF($S58<>"表示",0,IF($H58>0,$H58,IFERROR($E58*$G58,0)))) | J58: 1 | K58: 式 | M58: 10000 | N58: =IF($A58="","",IF($S58<>"表示",0,IF($M58>0,$M58,IFERROR($J58*$L58,0)))) | O58: =IF($A58="","",$I58-$N58) | P58: =IF($A58="","",IFERROR($O58/$I58,0)) | Q58: 半人役ハン | S58: 表示
A59: 58 | B59: 浴室 | C59: 施工 | D59: 〃 入口四方化粧枠取付 | E59: 1 | F59: 式 | H59: 14200 | I59: =IF($A59="","",IF($S59<>"表示",0,IF($H59>0,$H59,IFERROR($E59*$G59,0)))) | J59: 1 | K59: 式 | M59: 10000 | N59: =IF($A59="","",IF($S59<>"表示",0,IF($M59>0,$M59,IFERROR($J59*$L59,0)))) | O59: =IF($A59="","",$I59-$N59) | P59: =IF($A59="","",IFERROR($O59/$I59,0)) | Q59: 半人役 | S59: 表示
A60: 59 | B60: 浴室 | C60: 施工 | D60: 〃 外壁サッシ廻り補修 | E60: 1 | F60: 式 | H60: 28500 | I60: =IF($A60="","",IF($S60<>"表示",0,IF($H60>0,$H60,IFERROR($E60*$G60,0)))) | J60: 1 | K60: 式 | M60: 20000 | N60: =IF($A60="","",IF($S60<>"表示",0,IF($M60>0,$M60,IFERROR($J60*$L60,0)))) | O60: =IF($A60="","",$I60-$N60) | P60: =IF($A60="","",IFERROR($O60/$I60,0)) | Q60: 1人役 | S60: 表示
A61: 60 | B61: 浴室 | C61: 施工 | D61: 左官工事 土間下地 | E61: 1 | F61: 式 | H61: 42800 | I61: =IF($A61="","",IF($S61<>"表示",0,IF($H61>0,$H61,IFERROR($E61*$G61,0)))) | J61: 1 | K61: 式 | M61: 30000 | N61: =IF($A61="","",IF($S61<>"表示",0,IF($M61>0,$M61,IFERROR($J61*$L61,0)))) | O61: =IF($A61="","",$I61-$N61) | P61: =IF($A61="","",IFERROR($O61/$I61,0)) | Q61: 1.5人役 | S61: 表示
A62: 61 | B62: 浴室 | C62: 施工 | D62: システムバス取付 | E62: 1 | F62: 式 | H62: 125700 | I62: =IF($A62="","",IF($S62<>"表示",0,IF($H62>0,$H62,IFERROR($E62*$G62,0)))) | J62: 1 | K62: 式 | M62: 88000 | N62: =IF($A62="","",IF($S62<>"表示",0,IF($M62>0,$M62,IFERROR($J62*$L62,0)))) | O62: =IF($A62="","",$I62-$N62) | P62: =IF($A62="","",IFERROR($O62/$I62,0)) | S62: 表示
A63: 62 | B63: 浴室 | C63: 施工 | D63: 給水給湯排水工事 | E63: 1 | F63: 式 | H63: 64200 | I63: =IF($A63="","",IF($S63<>"表示",0,IF($H63>0,$H63,IFERROR($E63*$G63,0)))) | J63: 1 | K63: 式 | M63: 45000 | N63: =IF($A63="","",IF($S63<>"表示",0,IF($M63>0,$M63,IFERROR($J63*$L63,0)))) | O63: =IF($A63="","",$I63-$N63) | P63: =IF($A63="","",IFERROR($O63/$I63,0)) | S63: 表示
A64: 63 | B64: 浴室 | C64: 施工 | D64: ガス給湯器取替え工事 | E64: 1 | F64: 式 | H64: 22800 | I64: =IF($A64="","",IF($S64<>"表示",0,IF($H64>0,$H64,IFERROR($E64*$G64,0)))) | J64: 1 | K64: 式 | M64: 16000 | N64: =IF($A64="","",IF($S64<>"表示",0,IF($M64>0,$M64,IFERROR($J64*$L64,0)))) | O64: =IF($A64="","",$I64-$N64) | P64: =IF($A64="","",IFERROR($O64/$I64,0)) | S64: 表示
A65: 64 | B65: 浴室 | C65: 施工 | D65: 電気及び換気工事 | E65: 1 | F65: 式 | H65: 40000 | I65: =IF($A65="","",IF($S65<>"表示",0,IF($H65>0,$H65,IFERROR($E65*$G65,0)))) | J65: 1 | K65: 式 | M65: 28000 | N65: =IF($A65="","",IF($S65<>"表示",0,IF($M65>0,$M65,IFERROR($J65*$L65,0)))) | O65: =IF($A65="","",$I65-$N65) | P65: =IF($A65="","",IFERROR($O65/$I65,0)) | S65: 表示
A66: 65 | B66: 洗面所 | C66: 材料 | D66: 巾木 | E66: 2 | F66: 本 | G66: 900 | I66: =IF($A66="","",IF($S66<>"表示",0,IF($H66>0,$H66,IFERROR($E66*$G66,0)))) | J66: 2 | K66: 本 | L66: 735 | N66: =IF($A66="","",IF($S66<>"表示",0,IF($M66>0,$M66,IFERROR($J66*$L66,0)))) | O66: =IF($A66="","",$I66-$N66) | P66: =IF($A66="","",IFERROR($O66/$I66,0)) | Q66: 定価2,100円/本×35％ | R66: ノダ 巾木C 7×60×3,950㎜（3本入）☆ | S66: 表示
A67: 66 | B67: 洗面所 | C67: 材料 | D67: 片開き戸（ドアのみ） | E67: 1 | F67: セット | G67: 28000 | I67: =IF($A67="","",IF($S67<>"表示",0,IF($H67>0,$H67,IFERROR($E67*$G67,0)))) | J67: 1 | K67: セット | L67: 21000 | N67: =IF($A67="","",IF($S67<>"表示",0,IF($M67>0,$M67,IFERROR($J67*$L67,0)))) | O67: =IF($A67="","",$I67-$N67) | P67: =IF($A67="","",IFERROR($O67/$I67,0)) | R67: 別注 明かり窓付フラッシュドア 金物含む | S67: 表示
A68: 67 | B68: 洗面所 | C68: 材料 | D68: 洗面化粧台 3面鏡 間口75㎝ | E68: 1 | F68: セット | G68: 57900 | I68: =IF($A68="","",IF($S68<>"表示",0,IF($H68>0,$H68,IFERROR($E68*$G68,0)))) | J68: 1 | K68: セット | L68: 43460 | N68: =IF($A68="","",IF($S68<>"表示",0,IF($M68>0,$M68,IFERROR($J68*$L68,0)))) | O68: =IF($A68="","",$I68-$N68) | P68: =IF($A68="","",IFERROR($O68/$I68,0)) | Q68: 定価802,100円/本×33％ | R68: TOTO Vシリーズ 開き扉 ☆ | S68: 表示
A69: 68 | B69: 洗面所 | C69: 材料 | D69: タオル掛け（バータイプ）44.8㎝ | E69: 1 | F69: 台 | G69: 1700 | I69: =IF($A69="","",IF($S69<>"表示",0,IF($H69>0,$H69,IFERROR($E69*$G69,0)))) | J69: 1 | K69: 台 | L69: 1325 | N69: =IF($A69="","",IF($S69<>"表示",0,IF($M69>0,$M69,IFERROR($J69*$L69,0)))) | O69: =IF($A69="","",$I69-$N69) | P69: =IF($A69="","",IFERROR($O69/$I69,0)) | Q69: 定価24,500円/本×33％ | R69: TOTO YT51S4R ☆ | S69: 表示
A70: 69 | B70: 洗面所 | C70: 材料 | D70: 木枠塗装材ザ | E70: 1 | F70: 式 | H70: 3200 | I70: =IF($A70="","",IF($S70<>"表示",0,IF($H70>0,$H70,IFERROR($E70*$G70,0)))) | J70: 1 | K70: 式 | M70: 2400 | N70: =IF($A70="","",IF($S70<>"表示",0,IF($M70>0,$M70,IFERROR($J70*$L70,0)))) | O70: =IF($A70="","",$I70-$N70) | P70: =IF($A70="","",IFERROR($O70/$I70,0)) | S70: 表示
A71: 70 | B71: 洗面所 | C71: 施工 | D71: 巾木取替え | E71: 6 | F71: m | G71: 850 | I71: =IF($A71="","",IF($S71<>"表示",0,IF($H71>0,$H71,IFERROR($E71*$G71,0)))) | J71: 6 | K71: m | L71: 600 | N71: =IF($A71="","",IF($S71<>"表示",0,IF($M71>0,$M71,IFERROR($J71*$L71,0)))) | O71: =IF($A71="","",$I71-$N71) | P71: =IF($A71="","",IFERROR($O71/$I71,0)) | S71: 表示
A72: 71 | B72: 洗面所 | C72: 施工 | D72: 片開き戸取替え | E72: 1 | F72: 式 | H72: 4200 | I72: =IF($A72="","",IF($S72<>"表示",0,IF($H72>0,$H72,IFERROR($E72*$G72,0)))) | J72: 1 | K72: 式 | M72: 3000 | N72: =IF($A72="","",IF($S72<>"表示",0,IF($M72>0,$M72,IFERROR($J72*$L72,0)))) | O72: =IF($A72="","",$I72-$N72) | P72: =IF($A72="","",IFERROR($O72/$I72,0)) | R72: 建付調整 | S72: 表示
A73: 72 | B73: 洗面所 | C73: 施工 | D73: 洗面台脱着工事 | E73: 1 | F73: 式 | H73: 20000 | I73: =IF($A73="","",IF($S73<>"表示",0,IF($H73>0,$H73,IFERROR($E73*$G73,0)))) | J73: 1 | K73: 式 | M73: 14000 | N73: =IF($A73="","",IF($S73<>"表示",0,IF($M73>0,$M73,IFERROR($J73*$L73,0)))) | O73: =IF($A73="","",$I73-$N73) | P73: =IF($A73="","",IFERROR($O73/$I73,0)) | R73: 電気結線含む | S73: 表示
A74: 73 | B74: 洗面所 | C74: 経費 | D74: 既存洗面化粧台廃棄費 | E74: 1 | F74: 式 | H74: 7100 | I74: =IF($A74="","",IF($S74<>"表示",0,IF($H74>0,$H74,IFERROR($E74*$G74,0)))) | J74: 1 | K74: 式 | M74: 5000 | N74: =IF($A74="","",IF($S74<>"表示",0,IF($M74>0,$M74,IFERROR($J74*$L74,0)))) | O74: =IF($A74="","",$I74-$N74) | P74: =IF($A74="","",IFERROR($O74/$I74,0)) | S74: 表示
A75: 74 | B75: 洗面所 | C75: 施工 | D75: タオル掛け取付 | E75: 1 | F75: 式 | H75: 1400 | I75: =IF($A75="","",IF($S75<>"表示",0,IF($H75>0,$H75,IFERROR($E75*$G75,0)))) | J75: 1 | K75: 式 | M75: 1000 | N75: =IF($A75="","",IF($S75<>"表示",0,IF($M75>0,$M75,IFERROR($J75*$L75,0)))) | O75: =IF($A75="","",$I75-$N75) | P75: =IF($A75="","",IFERROR($O75/$I75,0)) | S75: 表示
A76: 75 | B76: 洗面所 | C76: 施工 | D76: 床 クッションフロア貼替え | E76: 1 | F76: 式 | H76: 14200 | I76: =IF($A76="","",IF($S76<>"表示",0,IF($H76>0,$H76,IFERROR($E76*$G76,0)))) | J76: 1 | K76: 式 | M76: 10000 | N76: =IF($A76="","",IF($S76<>"表示",0,IF($M76>0,$M76,IFERROR($J76*$L76,0)))) | O76: =IF($A76="","",$I76-$N76) | P76: =IF($A76="","",IFERROR($O76/$I76,0)) | Q76: 材工共 | S76: 表示
A77: 76 | B77: 洗面所 | C77: 施工 | D77: 天井・壁 ビニールクロス貼替え | E77: 16 | F77: ㎡ | G77: 1140 | I77: =IF($A77="","",IF($S77<>"表示",0,IF($H77>0,$H77,IFERROR($E77*$G77,0)))) | J77: 16 | K77: ㎡ | L77: 650 | N77: =IF($A77="","",IF($S77<>"表示",0,IF($M77>0,$M77,IFERROR($J77*$L77,0)))) | O77: =IF($A77="","",$I77-$N77) | P77: =IF($A77="","",IFERROR($O77/$I77,0)) | Q77: 材工共 | R77: 量産品 SP | S77: 表示
A78: 77 | B78: 洗面所 | C78: 施工 | D78: 木枠塗装 | E78: 1 | F78: 式 | H78: 4200 | I78: =IF($A78="","",IF($S78<>"表示",0,IF($H78>0,$H78,IFERROR($E78*$G78,0)))) | J78: 1 | K78: 式 | M78: 3000 | N78: =IF($A78="","",IF($S78<>"表示",0,IF($M78>0,$M78,IFERROR($J78*$L78,0)))) | O78: =IF($A78="","",$I78-$N78) | P78: =IF($A78="","",IFERROR($O78/$I78,0)) | S78: 表示
A79: 78 | B79: 洗面所 | C79: 施工 | D79: プレート取替え | E79: 2 | F79: セット | G79: 850 | I79: =IF($A79="","",IF($S79<>"表示",0,IF($H79>0,$H79,IFERROR($E79*$G79,0)))) | J79: 2 | K79: セット | L79: 600 | N79: =IF($A79="","",IF($S79<>"表示",0,IF($M79>0,$M79,IFERROR($J79*$L79,0)))) | O79: =IF($A79="","",$I79-$N79) | P79: =IF($A79="","",IFERROR($O79/$I79,0)) | Q79: 材工共 | S79: 表示
A80: 79 | B80: トイレ | C80: 材料 | D80: 巾木 | E80: 2 | F80: 本 | G80: 900 | I80: =IF($A80="","",IF($S80<>"表示",0,IF($H80>0,$H80,IFERROR($E80*$G80,0)))) | J80: 2 | K80: 本 | L80: 735 | N80: =IF($A80="","",IF($S80<>"表示",0,IF($M80>0,$M80,IFERROR($J80*$L80,0)))) | O80: =IF($A80="","",$I80-$N80) | P80: =IF($A80="","",IFERROR($O80/$I80,0)) | Q80: 定価2,010円/本×35％ | R80: ノダ 巾木C 7×60×3,950㎜（3本入） ☆イ | S80: 表示
A81: 80 | B81: トイレ | C81: 材料 | D81: 片開き戸（ドアのみ） | E81: 1 | F81: セット | G81: 28000 | I81: =IF($A81="","",IF($S81<>"表示",0,IF($H81>0,$H81,IFERROR($E81*$G81,0)))) | J81: 1 | K81: セット | L81: 21000 | N81: =IF($A81="","",IF($S81<>"表示",0,IF($M81>0,$M81,IFERROR($J81*$L81,0)))) | O81: =IF($A81="","",$I81-$N81) | P81: =IF($A81="","",IFERROR($O81/$I81,0)) | R81: 別注 明かり窓付フラッシュ戸 金物含む | S81: 表示
A82: 81 | B82: トイレ | C82: 材料 | D82: 便器（床排水・リフォームタイプ）＋温水洗浄便座 | E82: 1 | F82: セット | G82: 97200 | I82: =IF($A82="","",IF($S82<>"表示",0,IF($H82>0,$H82,IFERROR($E82*$G82,0)))) | J82: 1 | K82: セット | L82: 72912 | N82: =IF($A82="","",IF($S82<>"表示",0,IF($M82>0,$M82,IFERROR($J82*$L82,0)))) | O82: =IF($A82="","",$I82-$N82) | P82: =IF($A82="","",IFERROR($O82/$I82,0)) | Q82: 定価173,600円×42％ | R82: TOTO ピュアレストQR＋ウォシュレットJ2 ☆ | S82: 表示
A83: 82 | B83: トイレ | C83: 材料 | D83: ペーパーホルダー | E83: 1 | F83: 台 | G83: 1700 | I83: =IF($A83="","",IF($S83<>"表示",0,IF($H83>0,$H83,IFERROR($E83*$G83,0)))) | J83: 1 | K83: 台 | L83: 1325 | N83: =IF($A83="","",IF($S83<>"表示",0,IF($M83>0,$M83,IFERROR($J83*$L83,0)))) | O83: =IF($A83="","",$I83-$N83) | P83: =IF($A83="","",IFERROR($O83/$I83,0)) | Q83: 定価2,650円×50％ | R83: TOTO YH51R ☆ | S83: 表示
A84: 83 | B84: トイレ | C84: 材料 | D84: タオル掛け（リングタイプ） | E84: 1 | F84: 台ダ | G84: 1700 | I84: =IF($A84="","",IF($S84<>"表示",0,IF($H84>0,$H84,IFERROR($E84*$G84,0)))) | J84: 1 | K84: 台ダ | L84: 1325 | N84: =IF($A84="","",IF($S84<>"表示",0,IF($M84>0,$M84,IFERROR($J84*$L84,0)))) | O84: =IF($A84="","",$I84-$N84) | P84: =IF($A84="","",IFERROR($O84/$I84,0)) | Q84: 定価2,650円×50％ | R84: TOTO YH51R ☆ | S84: 表示
A85: 84 | B85: トイレ | C85: 材料 | D85: 木枠塗装剤 | E85: 1 | F85: 式 | H85: 3200 | I85: =IF($A85="","",IF($S85<>"表示",0,IF($H85>0,$H85,IFERROR($E85*$G85,0)))) | J85: 1 | K85: 式 | M85: 2400 | N85: =IF($A85="","",IF($S85<>"表示",0,IF($M85>0,$M85,IFERROR($J85*$L85,0)))) | O85: =IF($A85="","",$I85-$N85) | P85: =IF($A85="","",IFERROR($O85/$I85,0)) | S85: 表示
A86: 85 | B86: トイレ | C86: 施工 | D86: 巾木取替え | E86: 4.5 | F86: m | G86: 850 | I86: =IF($A86="","",IF($S86<>"表示",0,IF($H86>0,$H86,IFERROR($E86*$G86,0)))) | J86: 4.5 | K86: m | L86: 600 | N86: =IF($A86="","",IF($S86<>"表示",0,IF($M86>0,$M86,IFERROR($J86*$L86,0)))) | O86: =IF($A86="","",$I86-$N86) | P86: =IF($A86="","",IFERROR($O86/$I86,0)) | S86: 表示
A87: 86 | B87: トイレ | C87: 施工 | D87: 片開き戸取替え | E87: 1 | F87: 式 | H87: 4200 | I87: =IF($A87="","",IF($S87<>"表示",0,IF($H87>0,$H87,IFERROR($E87*$G87,0)))) | J87: 1 | K87: 式 | M87: 3000 | N87: =IF($A87="","",IF($S87<>"表示",0,IF($M87>0,$M87,IFERROR($J87*$L87,0)))) | O87: =IF($A87="","",$I87-$N87) | P87: =IF($A87="","",IFERROR($O87/$I87,0)) | R87: 建付調整 | S87: 表示
A88: 87 | B88: トイレ | C88: 施工 | D88: 便器脱着工事 | E88: 1 | F88: 式 | H88: 42800 | I88: =IF($A88="","",IF($S88<>"表示",0,IF($H88>0,$H88,IFERROR($E88*$G88,0)))) | J88: 1 | K88: 式 | M88: 30000 | N88: =IF($A88="","",IF($S88<>"表示",0,IF($M88>0,$M88,IFERROR($J88*$L88,0)))) | O88: =IF($A88="","",$I88-$N88) | P88: =IF($A88="","",IFERROR($O88/$I88,0)) | S88: 表示
A89: 88 | B89: トイレ | C89: 経費 | D89: 既存便器廃棄費 | E89: 1 | F89: 式 | H89: 4200 | I89: =IF($A89="","",IF($S89<>"表示",0,IF($H89>0,$H89,IFERROR($E89*$G89,0)))) | J89: 1 | K89: 式 | M89: 3000 | N89: =IF($A89="","",IF($S89<>"表示",0,IF($M89>0,$M89,IFERROR($J89*$L89,0)))) | O89: =IF($A89="","",$I89-$N89) | P89: =IF($A89="","",IFERROR($O89/$I89,0)) | S89: 表示
A90: 89 | B90: トイレ | C90: 施工 | D90: アクセサリー取付 | E90: 2 | F90: ヶ所 | G90: 1420 | I90: =IF($A90="","",IF($S90<>"表示",0,IF($H90>0,$H90,IFERROR($E90*$G90,0)))) | J90: 2 | K90: ヶ所 | L90: 1000 | N90: =IF($A90="","",IF($S90<>"表示",0,IF($M90>0,$M90,IFERROR($J90*$L90,0)))) | O90: =IF($A90="","",$I90-$N90) | P90: =IF($A90="","",IFERROR($O90/$I90,0)) | S90: 表示
A91: 90 | B91: トイレ | C91: 施工 | D91: 床 クッションフロア貼替え | E91: 1 | F91: 式 | H91: 11400 | I91: =IF($A91="","",IF($S91<>"表示",0,IF($H91>0,$H91,IFERROR($E91*$G91,0)))) | J91: 1 | K91: 式 | M91: 8000 | N91: =IF($A91="","",IF($S91<>"表示",0,IF($M91>0,$M91,IFERROR($J91*$L91,0)))) | O91: =IF($A91="","",$I91-$N91) | P91: =IF($A91="","",IFERROR($O91/$I91,0)) | Q91: 材工共ザコトモ | S91: 表示
A92: 91 | B92: トイレ | C92: 施工 | D92: 天井・壁 ビニールクロス貼替え | E92: 12 | F92: ㎡ | G92: 1140 | I92: =IF($A92="","",IF($S92<>"表示",0,IF($H92>0,$H92,IFERROR($E92*$G92,0)))) | J92: 12 | K92: ㎡ | L92: 650 | N92: =IF($A92="","",IF($S92<>"表示",0,IF($M92>0,$M92,IFERROR($J92*$L92,0)))) | O92: =IF($A92="","",$I92-$N92) | P92: =IF($A92="","",IFERROR($O92/$I92,0)) | Q92: 材工共ザコトモ | R92: 量産品 SP | S92: 表示
A93: 92 | B93: トイレ | C93: 施工 | D93: 木枠塗装 | E93: 1 | F93: 式 | H93: 4200 | I93: =IF($A93="","",IF($S93<>"表示",0,IF($H93>0,$H93,IFERROR($E93*$G93,0)))) | J93: 1 | K93: 式 | M93: 3000 | N93: =IF($A93="","",IF($S93<>"表示",0,IF($M93>0,$M93,IFERROR($J93*$L93,0)))) | O93: =IF($A93="","",$I93-$N93) | P93: =IF($A93="","",IFERROR($O93/$I93,0)) | S93: 表示
A94: 93 | B94: トイレ | C94: 施工 | D94: プレート取替 | E94: 2 | F94: セット | G94: 850 | I94: =IF($A94="","",IF($S94<>"表示",0,IF($H94>0,$H94,IFERROR($E94*$G94,0)))) | J94: 2 | K94: セット | L94: 600 | N94: =IF($A94="","",IF($S94<>"表示",0,IF($M94>0,$M94,IFERROR($J94*$L94,0)))) | O94: =IF($A94="","",$I94-$N94) | P94: =IF($A94="","",IFERROR($O94/$I94,0)) | Q94: 材工共ザコトモ | S94: 表示
A95: 94 | B95: 1F 和室6帖 | C95: 材料 | D95: 天井板（木目柄化粧合板） | E95: 3 | F95: 坪 | G95: 5300 | I95: =IF($A95="","",IF($S95<>"表示",0,IF($H95>0,$H95,IFERROR($E95*$G95,0)))) | J95: 3 | K95: 坪 | L95: 4000 | N95: =IF($A95="","",IF($S95<>"表示",0,IF($M95>0,$M95,IFERROR($J95*$L95,0)))) | O95: =IF($A95="","",$I95-$N95) | P95: =IF($A95="","",IFERROR($O95/$I95,0)) | S95: 表示
A96: 95 | B96: 1F 和室6帖 | C96: 材料 | D96: 戸襖（ドアのみ） | E96: 1 | F96: 枚 | G96: 24000 | I96: =IF($A96="","",IF($S96<>"表示",0,IF($H96>0,$H96,IFERROR($E96*$G96,0)))) | J96: 1 | K96: 枚 | L96: 18000 | N96: =IF($A96="","",IF($S96<>"表示",0,IF($M96>0,$M96,IFERROR($J96*$L96,0)))) | O96: =IF($A96="","",$I96-$N96) | P96: =IF($A96="","",IFERROR($O96/$I96,0)) | R96: 別注 明かり窓付フラッシュ戸 金物含む | S96: 表示
A97: 96 | B97: 1F 和室6帖 | C97: 施工 | D97: 畳表替え | E97: 6 | F97: 枚 | G97: 5420 | I97: =IF($A97="","",IF($S97<>"表示",0,IF($H97>0,$H97,IFERROR($E97*$G97,0)))) | J97: 6 | K97: 枚 | L97: 3800 | N97: =IF($A97="","",IF($S97<>"表示",0,IF($M97>0,$M97,IFERROR($J97*$L97,0)))) | O97: =IF($A97="","",$I97-$N97) | P97: =IF($A97="","",IFERROR($O97/$I97,0)) | S97: 表示
A98: 97 | B98: 1F 和室6帖 | C98: 施工 | D98: 天井板取替え | E98: 10 | F98: ㎡ | G98: 2850 | I98: =IF($A98="","",IF($S98<>"表示",0,IF($H98>0,$H98,IFERROR($E98*$G98,0)))) | J98: 10 | K98: ㎡ | L98: 2000 | N98: =IF($A98="","",IF($S98<>"表示",0,IF($M98>0,$M98,IFERROR($J98*$L98,0)))) | O98: =IF($A98="","",$I98-$N98) | P98: =IF($A98="","",IFERROR($O98/$I98,0)) | R98: 建付調整 | S98: 表示
A99: 98 | B99: 1F 和室6帖 | C99: 施工 | D99: 戸襖取替えト | E99: 1 | F99: 式 | H99: 4200 | I99: =IF($A99="","",IF($S99<>"表示",0,IF($H99>0,$H99,IFERROR($E99*$G99,0)))) | J99: 1 | K99: 式 | M99: 3000 | N99: =IF($A99="","",IF($S99<>"表示",0,IF($M99>0,$M99,IFERROR($J99*$L99,0)))) | O99: =IF($A99="","",$I99-$N99) | P99: =IF($A99="","",IFERROR($O99/$I99,0)) | S99: 表示
A100: 99 | B100: 1F 和室6帖 | C100: 施工 | D100: 襖貼替え 大 | E100: 3 | F100: 枚 | G100: 2850 | I100: =IF($A100="","",IF($S100<>"表示",0,IF($H100>0,$H100,IFERROR($E100*$G100,0)))) | J100: 3 | K100: 枚 | L100: 2000 | N100: =IF($A100="","",IF($S100<>"表示",0,IF($M100>0,$M100,IFERROR($J100*$L100,0)))) | O100: =IF($A100="","",$I100-$N100) | P100: =IF($A100="","",IFERROR($O100/$I100,0)) | S100: 表示
...

Sheet お客様見積書
A1: 御見積書
D3: 様 | F3: 作成日 | G3: ='設定'!$B$2
A4: 工事名 | B4: リフォーム工事一式 | F4: 会社名 | G4: ='設定'!$B$6
F5: 代表 | G5: ='設定'!$B$7
A7: 工区・部屋 | B7: 小計（税抜） | C7: 消費税 | D7: 税込金額 | E7: 備考
A8: 玄関ホール、廊下、階段室吹抜 | B8: =SUMIFS('入力シート'!$I$2:$I$301,'入力シート'!$B$2:$B$301,$A8,'入力シート'!$S$2:$S$301,"表示") | C8: =ROUNDDOWN(B8*'設定'!$B$3,0) | D8: =B8+C8
A9: LDK | B9: =SUMIFS('入力シート'!$I$2:$I$301,'入力シート'!$B$2:$B$301,$A9,'入力シート'!$S$2:$S$301,"表示") | C9: =ROUNDDOWN(B9*'設定'!$B$3,0) | D9: =B9+C9
A10: 浴室 | B10: =SUMIFS('入力シート'!$I$2:$I$301,'入力シート'!$B$2:$B$301,$A10,'入力シート'!$S$2:$S$301,"表示") | C10: =ROUNDDOWN(B10*'設定'!$B$3,0) | D10: =B10+C10
A11: 洗面所 | B11: =SUMIFS('入力シート'!$I$2:$I$301,'入力シート'!$B$2:$B$301,$A11,'入力シート'!$S$2:$S$301,"表示") | C11: =ROUNDDOWN(B11*'設定'!$B$3,0) | D11: =B11+C11
A12: トイレ | B12: =SUMIFS('入力シート'!$I$2:$I$301,'入力シート'!$B$2:$B$301,$A12,'入力シート'!$S$2:$S$301,"表示") | C12: =ROUNDDOWN(B12*'設定'!$B$3,0) | D12: =B12+C12
A13: 1F 和室6帖 | B13: =SUMIFS('入力シート'!$I$2:$I$301,'入力シート'!$B$2:$B$301,$A13,'入力シート'!$S$2:$S$301,"表示") | C13: =ROUNDDOWN(B13*'設定'!$B$3,0) | D13: =B13+C13
A14: 2F 和室 4.5帖 | B14: =SUMIFS('入力シート'!$I$2:$I$301,'入力シート'!$B$2:$B$301,$A14,'入力シート'!$S$2:$S$301,"表示") | C14: =ROUNDDOWN(B14*'設定'!$B$3,0) | D14: =B14+C14
A15: 2F 洋間8帖 A | B15: =SUMIFS('入力シート'!$I$2:$I$301,'入力シート'!$B$2:$B$301,$A15,'入力シート'!$S$2:$S$301,"表示") | C15: =ROUNDDOWN(B15*'設定'!$B$3,0) | D15: =B15+C15
A16: 2F 洋間6帖 B | B16: =SUMIFS('入力シート'!$I$2:$I$301,'入力シート'!$B$2:$B$301,$A16,'入力シート'!$S$2:$S$301,"表示") | C16: =ROUNDDOWN(B16*'設定'!$B$3,0) | D16: =B16+C16
A17: 2F 廊下 | B17: =SUMIFS('入力シート'!$I$2:$I$301,'入力シート'!$B$2:$B$301,$A17,'入力シート'!$S$2:$S$301,"表示") | C17: =ROUNDDOWN(B17*'設定'!$B$3,0) | D17: =B17+C17
A18: 屋根 | B18: =SUMIFS('入力シート'!$I$2:$I$301,'入力シート'!$B$2:$B$301,$A18,'入力シート'!$S$2:$S$301,"表示") | C18: =ROUNDDOWN(B18*'設定'!$B$3,0) | D18: =B18+C18
A19: 外壁 | B19: =SUMIFS('入力シート'!$I$2:$I$301,'入力シート'!$B$2:$B$301,$A19,'入力シート'!$S$2:$S$301,"表示") | C19: =ROUNDDOWN(B19*'設定'!$B$3,0) | D19: =B19+C19
A20: 未分類（下記一覧にない工区） | B20: =SUMIFS('入力シート'!$I$2:$I$301,'入力シート'!$S$2:$S$301,"表示")-SUM(B8:B19) | C20: =ROUNDDOWN(B20*'設定'!$B$3,0) | D20: =B20+C20
A21: 値引き（税抜・マイナスで入力） | B21: 0 | C21: =-ROUNDDOWN(-B21*'設定'!$B$3,0) | D21: =B21+C21
A22: 合計 | B22: =SUM(B8:B21) | C22: =SUM(C8:C21) | D22: =SUM(D8:D21)
A24: お支払条件 | B24: ='設定'!$B$10
A25: 見積有効期限 | B25: ='設定'!$B$2+'設定'!$B$9
A26: 振込先 | B26: ='設定'!$B$11
A27: 特記事項 | B27: ='設定'!$B$12

Sheet お客様見積書_詳細
A1: No | B1: 部屋・工区 | C1: 工事項目 | D1: 数量 | E1: 単位 | F1: 単価 | G1: 金額 | H1: 備考
A2: =IFERROR(IF('入力シート'!$S2="表示",'入力シート'!A2,""),"") | B2: =IFERROR(IF('入力シート'!$S2="表示",'入力シート'!B2,""),"") | C2: =IFERROR(IF('入力シート'!$S2="表示",'入力シート'!D2,""),"") | D2: =IFERROR(IF('入力シート'!$S2="表示",'入力シート'!E2,""),"") | E2: =IFERROR(IF('入力シート'!$S2="表示",'入力シート'!F2,""),"") | F2: =IFERROR(IF('入力シート'!$S2="表示",'入力シート'!G2,""),"") | G2: =IFERROR(IF('入力シート'!$S2="表示",'入力シート'!I2,""),"") | H2: =IFERROR(IF('入力シート'!$S2="表示",'入力シート'!R2,""),"")
A3: =IFERROR(IF('入力シート'!$S3="表示",'入力シート'!A3,""),"") | B3: =IFERROR(IF('入力シート'!$S3="表示",'入力シート'!B3,""),"") | C3: =IFERROR(IF('入力シート'!$S3="表示",'入力シート'!D3,""),"") | D3: =IFERROR(IF('入力シート'!$S3="表示",'入力シート'!E3,""),"") | E3: =IFERROR(IF('入力シート'!$S3="表示",'入力シート'!F3,""),"") | F3: =IFERROR(IF('入力シート'!$S3="表示",'入力シート'!G3,""),"") | G3: =IFERROR(IF('入力シート'!$S3="表示",'入力シート'!I3,""),"") | H3: =IFERROR(IF('入力シート'!$S3="表示",'入力シート'!R3,""),"")
A4: =IFERROR(IF('入力シート'!$S4="表示",'入力シート'!A4,""),"") | B4: =IFERROR(IF('入力シート'!$S4="表示",'入力シート'!B4,""),"") | C4: =IFERROR(IF('入力シート'!$S4="表示",'入力シート'!D4,""),"") | D4: =IFERROR(IF('入力シート'!$S4="表示",'入力シート'!E4,""),"") | E4: =IFERROR(IF('入力シート'!$S4="表示",'入力シート'!F4,""),"") | F4: =IFERROR(IF('入力シート'!$S4="表示",'入力シート'!G4,""),"") | G4: =IFERROR(IF('入力シート'!$S4="表示",'入力シート'!I4,""),"") | H4: =IFERROR(IF('入力シート'!$S4="表示",'入力シート'!R4,""),"")
A5: =IFERROR(IF('入力シート'!$S5="表示",'入力シート'!A5,""),"") | B5: =IFERROR(IF('入力シート'!$S5="表示",'入力シート'!B5,""),"") | C5: =IFERROR(IF('入力シート'!$S5="表示",'入力シート'!D5,""),"") | D5: =IFERROR(IF('入力シート'!$S5="表示",'入力シート'!E5,""),"") | E5: =IFERROR(IF('入力シート'!$S5="表示",'入力シート'!F5,""),"") | F5: =IFERROR(IF('入力シート'!$S5="表示",'入力シート'!G5,""),"") | G5: =IFERROR(IF('入力シート'!$S5="表示",'入力シート'!I5,""),"") | H5: =IFERROR(IF('入力シート'!$S5="表示",'入力シート'!R5,""),"")
A6: =IFERROR(IF('入力シート'!$S6="表示",'入力シート'!A6,""),"") | B6: =IFERROR(IF('入力シート'!$S6="表示",'入力シート'!B6,""),"") | C6: =IFERROR(IF('入力シート'!$S6="表示",'入力シート'!D6,""),"") | D6: =IFERROR(IF('入力シート'!$S6="表示",'入力シート'!E6,""),"") | E6: =IFERROR(IF('入力シート'!$S6="表示",'入力シート'!F6,""),"") | F6: =IFERROR(IF('入力シート'!$S6="表示",'入力シート'!G6,""),"") | G6: =IFERROR(IF('入力シート'!$S6="表示",'入力シート'!I6,""),"") | H6: =IFERROR(IF('入力シート'!$S6="表示",'入力シート'!R6,""),"")
A7: =IFERROR(IF('入力シート'!$S7="表示",'入力シート'!A7,""),"") | B7: =IFERROR(IF('入力シート'!$S7="表示",'入力シート'!B7,""),"") | C7: =IFERROR(IF('入力シート'!$S7="表示",'入力シート'!D7,""),"") | D7: =IFERROR(IF('入力シート'!$S7="表示",'入力シート'!E7,""),"") | E7: =IFERROR(IF('入力シート'!$S7="表示",'入力シート'!F7,""),"") | F7: =IFERROR(IF('入力シート'!$S7="表示",'入力シート'!G7,""),"") | G7: =IFERROR(IF('入力シート'!$S7="表示",'入力シート'!I7,""),"") | H7: =IFERROR(IF('入力シート'!$S7="表示",'入力シート'!R7,""),"")
A8: =IFERROR(IF('入力シート'!$S8="表示",'入力シート'!A8,""),"") | B8: =IFERROR(IF('入力シート'!$S8="表示",'入力シート'!B8,""),"") | C8: =IFERROR(IF('入力シート'!$S8="表示",'入力シート'!D8,""),"") | D8: =IFERROR(IF('入力シート'!$S8="表示",'入力シート'!E8,""),"") | E8: =IFERROR(IF('入力シート'!$S8="表示",'入力シート'!F8,""),"") | F8: =IFERROR(IF('入力シート'!$S8="表示",'入力シート'!G8,""),"") | G8: =IFERROR(IF('入力シート'!$S8="表示",'入力シート'!I8,""),"") | H8: =IFERROR(IF('入力シート'!$S8="表示",'入力シート'!R8,""),"")
A9: =IFERROR(IF('入力シート'!$S9="表示",'入力シート'!A9,""),"") | B9: =IFERROR(IF('入力シート'!$S9="表示",'入力シート'!B9,""),"") | C9: =IFERROR(IF('入力シート'!$S9="表示",'入力シート'!D9,""),"") | D9: =IFERROR(IF('入力シート'!$S9="表示",'入力シート'!E9,""),"") | E9: =IFERROR(IF('入力シート'!$S9="表示",'入力シート'!F9,""),"") | F9: =IFERROR(IF('入力シート'!$S9="表示",'入力シート'!G9,""),"") | G9: =IFERROR(IF('入力シート'!$S9="表示",'入力シート'!I9,""),"") | H9: =IFERROR(IF('入力シート'!$S9="表示",'入力シート'!R9,""),"")
A10: =IFERROR(IF('入力シート'!$S10="表示",'入力シート'!A10,""),"") | B10: =IFERROR(IF('入力シート'!$S10="表示",'入力シート'!B10,""),"") | C10: =IFERROR(IF('入力シート'!$S10="表示",'入力シート'!D10,""),"") | D10: =IFERROR(IF('入力シート'!$S10="表示",'入力シート'!E10,""),"") | E10: =IFERROR(IF('入力シート'!$S10="表示",'入力シート'!F10,""),"") | F10: =IFERROR(IF('入力シート'!$S10="表示",'入力シート'!G10,""),"") | G10: =IFERROR(IF('入力シート'!$S10="表示",'入力シート'!I10,""),"") | H10: =IFERROR(IF('入力シート'!$S10="表示",'入力シート'!R10,""),"")
A11: =IFERROR(IF('入力シート'!$S11="表示",'入力シート'!A11,""),"") | B11: =IFERROR(IF('入力シート'!$S11="表示",'入力シート'!B11,""),"") | C11: =IFERROR(IF('入力シート'!$S11="表示",'入力シート'!D11,""),"") | D11: =IFERROR(IF('入力シート'!$S11="表示",'入力シート'!E11,""),"") | E11: =IFERROR(IF('入力シート'!$S11="表示",'入力シート'!F11,""),"") | F11: =IFERROR(IF('入力シート'!$S11="表示",'入力シート'!G11,""),"") | G11: =IFERROR(IF('入力シート'!$S11="表示",'入力シート'!I11,""),"") | H11: =IFERROR(IF('入力シート'!$S11="表示",'入力シート'!R11,""),"")
A12: =IFERROR(IF('入力シート'!$S12="表示",'入力シート'!A12,""),"") | B12: =IFERROR(IF('入力シート'!$S12="表示",'入力シート'!B12,""),"") | C12: =IFERROR(IF('入力シート'!$S12="表示",'入力シート'!D12,""),"") | D12: =IFERROR(IF('入力シート'!$S12="表示",'入力シート'!E12,""),"") | E12: =IFERROR(IF('入力シート'!$S12="表示",'入力シート'!F12,""),"") | F12: =IFERROR(IF('入力シート'!$S12="表示",'入力シート'!G12,""),"") | G12: =IFERROR(IF('入力シート'!$S12="表示",'入力シート'!I12,""),"") | H12: =IFERROR(IF('入力シート'!$S12="表示",'入力シート'!R12,""),"")
A13: =IFERROR(IF('入力シート'!$S13="表示",'入力シート'!A13,""),"") | B13: =IFERROR(IF('入力シート'!$S13="表示",'入力シート'!B13,""),"") | C13: =IFERROR(IF('入力シート'!$S13="表示",'入力シート'!D13,""),"") | D13: =IFERROR(IF('入力シート'!$S13="表示",'入力シート'!E13,""),"") | E13: =IFERROR(IF('入力シート'!$S13="表示",'入力シート'!F13,""),"") | F13: =IFERROR(IF('入力シート'!$S13="表示",'入力シート'!G13,""),"") | G13: =IFERROR(IF('入力シート'!$S13="表示",'入力シート'!I13,""),"") | H13: =IFERROR(IF('入力シート'!$S13="表示",'入力シート'!R13,""),"")
... A301: =IFERROR(IF('入力シート'!$S301="表示",'入力シート'!A301,""),"") | B301: =IFERROR(IF('入力シート'!$S301="表示",'入力シート'!B301,""),"") | C301: =IFERROR(IF('入力シート'!$S301="表示",'入力シート'!D301,""),"") | D301: =IFERROR(IF('入力シート'!$S301="表示",'入力シート'!E301,""),"") | E301: =IFERROR(IF('入力シート'!$S301="表示",'入力シート'!F301,""),"") | F301: =IFERROR(IF('入力シート'!$S301="表示",'入力シート'!G301,""),"") | G301: =IFERROR(IF('入力シート'!$S301="表示",'入力シート'!I301,""),"") | H301: =IFERROR(IF('入力シート'!$S301="表示",'入力シート'!R301,""),"")

Sheet 社内実行予算書
A1: 社内実行予算書
A3: 工区・部屋 | B3: お客様見積 | C3: 社内実行予算 | D3: 粗利額 | E3: 粗利率 | F3: 目標粗利率 | G3: 判定 | H3: 備考
A4: 玄関ホール、廊下、階段室吹抜 | B4: =SUMIFS('入力シート'!$I$2:$I$301,'入力シート'!$B$2:$B$301,$A4,'入力シート'!$S$2:$S$301,"表示") | C4: =SUMIFS('入力シート'!$N$2:$N$301,'入力シート'!$B$2:$B$301,$A4,'入力シート'!$S$2:$S$301,"表示") | D4: =B4-C4 | E4: =IFERROR(D4/B4,0) | F4: ='設定'!$B$4 | G4: =IF(E4>='設定'!$B$4,"OK",IF(E4>='設定'!$B$5,"注意","要改善"))
A5: LDK | B5: =SUMIFS('入力シート'!$I$2:$I$301,'入力シート'!$B$2:$B$301,$A5,'入力シート'!$S$2:$S$301,"表示") | C5: =SUMIFS('入力シート'!$N$2:$N$301,'入力シート'!$B$2:$B$301,$A5,'入力シート'!$S$2:$S$301,"表示") | D5: =B5-C5 | E5: =IFERROR(D5/B5,0) | F5: ='設定'!$B$4 | G5: =IF(E5>='設定'!$B$4,"OK",IF(E5>='設定'!$B$5,"注意","要改善"))
A6: 浴室 | B6: =SUMIFS('入力シート'!$I$2:$I$301,'入力シート'!$B$2:$B$301,$A6,'入力シート'!$S$2:$S$301,"表示") | C6: =SUMIFS('入力シート'!$N$2:$N$301,'入力シート'!$B$2:$B$301,$A6,'入力シート'!$S$2:$S$301,"表示") | D6: =B6-C6 | E6: =IFERROR(D6/B6,0) | F6: ='設定'!$B$4 | G6: =IF(E6>='設定'!$B$4,"OK",IF(E6>='設定'!$B$5,"注意","要改善"))
A7: 洗面所 | B7: =SUMIFS('入力シート'!$I$2:$I$301,'入力シート'!$B$2:$B$301,$A7,'入力シート'!$S$2:$S$301,"表示") | C7: =SUMIFS('入力シート'!$N$2:$N$301,'入力シート'!$B$2:$B$301,$A7,'入力シート'!$S$2:$S$301,"表示") | D7: =B7-C7 | E7: =IFERROR(D7/B7,0) | F7: ='設定'!$B$4 | G7: =IF(E7>='設定'!$B$4,"OK",IF(E7>='設定'!$B$5,"注意","要改善"))
A8: トイレ | B8: =SUMIFS('入力シート'!$I$2:$I$301,'入力シート'!$B$2:$B$301,$A8,'入力シート'!$S$2:$S$301,"表示") | C8: =SUMIFS('入力シート'!$N$2:$N$301,'入力シート'!$B$2:$B$301,$A8,'入力シート'!$S$2:$S$301,"表示") | D8: =B8-C8 | E8: =IFERROR(D8/B8,0) | F8: ='設定'!$B$4 | G8: =IF(E8>='設定'!$B$4,"OK",IF(E8>='設定'!$B$5,"注意","要改善"))
A9: 1F 和室6帖 | B9: =SUMIFS('入力シート'!$I$2:$I$301,'入力シート'!$B$2:$B$301,$A9,'入力シート'!$S$2:$S$301,"表示") | C9: =SUMIFS('入力シート'!$N$2:$N$301,'入力シート'!$B$2:$B$301,$A9,'入力シート'!$S$2:$S$301,"表示") | D9: =B9-C9 | E9: =IFERROR(D9/B9,0) | F9: ='設定'!$B$4 | G9: =IF(E9>='設定'!$B$4,"OK",IF(E9>='設定'!$B$5,"注意","要改善"))
A10: 2F 和室 4.5帖 | B10: =SUMIFS('入力シート'!$I$2:$I$301,'入力シート'!$B$2:$B$301,$A10,'入力シート'!$S$2:$S$301,"表示") | C10: =SUMIFS('入力シート'!$N$2:$N$301,'入力シート'!$B$2:$B$301,$A10,'入力シート'!$S$2:$S$301,"表示") | D10: =B10-C10 | E10: =IFERROR(D10/B10,0) | F10: ='設定'!$B$4 | G10: =IF(E10>='設定'!$B$4,"OK",IF(E10>='設定'!$B$5,"注意","要改善"))
A11: 2F 洋間8帖 A | B11: =SUMIFS('入力シート'!$I$2:$I$301,'入力シート'!$B$2:$B$301,$A11,'入力シート'!$S$2:$S$301,"表示") | C11: =SUMIFS('入力シート'!$N$2:$N$301,'入力シート'!$B$2:$B$301,$A11,'入力シート'!$S$2:$S$301,"表示") | D11: =B11-C11 | E11: =IFERROR(D11/B11,0) | F11: ='設定'!$B$4 | G11: =IF(E11>='設定'!$B$4,"OK",IF(E11>='設定'!$B$5,"注意","要改善"))
A12: 2F 洋間6帖 B | B12: =SUMIFS('入力シート'!$I$2:$I$301,'入力シート'!$B$2:$B$301,$A12,'入力シート'!$S$2:$S$301,"表示") | C12: =SUMIFS('入力シート'!$N$2:$N$301,'入力シート'!$B$2:$B$301,$A12,'入力シート'!$S$2:$S$301,"表示") | D12: =B12-C12 | E12: =IFERROR(D12/B12,0) | F12: ='設定'!$B$4 | G12: =IF(E12>='設定'!$B$4,"OK",IF(E12>='設定'!$B$5,"注意","要改善"))
A13: 2F 廊下 | B13: =SUMIFS('入力シート'!$I$2:$I$301,'入力シート'!$B$2:$B$301,$A13,'入力シート'!$S$2:$S$301,"表示") | C13: =SUMIFS('入力シート'!$N$2:$N$301,'入力シート'!$B$2:$B$301,$A13,'入力シート'!$S$2:$S$301,"表示") | D13: =B13-C13 | E13: =IFERROR(D13/B13,0) | F13: ='設定'!$B$4 | G13: =IF(E13>='設定'!$B$4,"OK",IF(E13>='設定'!$B$5,"注意","要改善"))
A14: 屋根 | B14: =SUMIFS('入力シート'!$I$2:$I$301,'入力シート'!$B$2:$B$301,$A14,'入力シート'!$S$2:$S$301,"表示") | C14: =SUMIFS('入力シート'!$N$2:$N$301,'入力シート'!$B$2:$B$301,$A14,'入力シート'!$S$2:$S$301,"表示") | D14: =B14-C14 | E14: =IFERROR(D14/B14,0) | F14: ='設定'!$B$4 | G14: =IF(E14>='設定'!$B$4,"OK",IF(E14>='設定'!$B$5,"注意","要改善"))
A15: 外壁 | B15: =SUMIFS('入力シート'!$I$2:$I$301,'入力シート'!$B$2:$B$301,$A15,'入力シート'!$S$2:$S$301,"表示") | C15: =SUMIFS('入力シート'!$N$2:$N$301,'入力シート'!$B$2:$B$301,$A15,'入力シート'!$S$2:$S$301,"表示") | D15: =B15-C15 | E15: =IFERROR(D15/B15,0) | F15: ='設定'!$B$4 | G15: =IF(E15>='設定'!$B$4,"OK",IF(E15>='設定'!$B$5,"注意","要改善"))
A16: 未分類（下記一覧にない工区） | B16: =SUMIFS('入力シート'!$I$2:$I$301,'入力シート'!$S$2:$S$301,"表示")-SUM(B4:B15) | C16: =SUMIFS('入力シート'!$N$2:$N$301,'入力シート'!$S$2:$S$301,"表示")-SUM(C4:C15) | D16: =B16-C16 | E16: =IFERROR(D16/B16,0) | F16: ='設定'!$B$4 | G16: =IF(B16=0,"",IF(E16>='設定'!$B$4,"OK",IF(E16>='設定'!$B$5,"注意","要改善")))
A17: 値引き（税抜） | B17: ='お客様見積書'!B21 | C17: 0 | D17: =B17-C17
A18: 合計（値引後） | B18: =SUM(B4:B17) | C18: =SUM(C4:C17) | D18: =B18-C18 | E18: =IFERROR(D18/B18,0) | F18: ='設定'!$B$4 | G18: =IF(E18>='設定'!$B$4,"OK",IF(E18>='設定'!$B$5,"注意","要改善"))

Sheet 社内実行予算書_明細
A1: No | B1: 部屋・工区 | C1: カテゴリ | D1: 工事項目 | E1: お客様金額 | F1: 実行金額 | G1: 粗利額 | H1: 粗利率 | I1: 定価・掛率・人工費 | J1: 商品名・メーカー | K1: 判定
A2: =IFERROR(IF('入力シート'!$A2="","",'入力シート'!A2),"") | B2: =IFERROR(IF('入力シート'!$A2="","",'入力シート'!B2),"") | C2: =IFERROR(IF('入力シート'!$A2="","",'入力シート'!C2),"") | D2: =IFERROR(IF('入力シート'!$A2="","",'入力シート'!D2),"") | E2: =IFERROR(IF('入力シート'!$A2="","",'入力シート'!I2),"") | F2: =IFERROR(IF('入力シート'!$A2="","",'入力シート'!N2),"") | G2: =IFERROR(IF('入力シート'!$A2="","",'入力シート'!O2),"") | H2: =IFERROR(IF('入力シート'!$A2="","",'入力シート'!P2),"") | I2: =IFERROR(IF('入力シート'!$A2="","",'入力シート'!Q2),"") | J2: =IFERROR(IF('入力シート'!$A2="","",'入力シート'!R2),"") | K2: =IFERROR(IF('入力シート'!$A2="","",IF(H2>='設定'!$B$4,"OK",IF(H2>='設定'!$B$5,"注意","要改善"))),"")
A3: =IFERROR(IF('入力シート'!$A3="","",'入力シート'!A3),"") | B3: =IFERROR(IF('入力シート'!$A3="","",'入力シート'!B3),"") | C3: =IFERROR(IF('入力シート'!$A3="","",'入力シート'!C3),"") | D3: =IFERROR(IF('入力シート'!$A3="","",'入力シート'!D3),"") | E3: =IFERROR(IF('入力シート'!$A3="","",'入力シート'!I3),"") | F3: =IFERROR(IF('入力シート'!$A3="","",'入力シート'!N3),"") | G3: =IFERROR(IF('入力シート'!$A3="","",'入力シート'!O3),"") | H3: =IFERROR(IF('入力シート'!$A3="","",'入力シート'!P3),"") | I3: =IFERROR(IF('入力シート'!$A3="","",'入力シート'!Q3),"") | J3: =IFERROR(IF('入力シート'!$A3="","",'入力シート'!R3),"") | K3: =IFERROR(IF('入力シート'!$A3="","",IF(H3>='設定'!$B$4,"OK",IF(H3>='設定'!$B$5,"注意","要改善"))),"")
A4: =IFERROR(IF('入力シート'!$A4="","",'入力シート'!A4),"") | B4: =IFERROR(IF('入力シート'!$A4="","",'入力シート'!B4),"") | C4: =IFERROR(IF('入力シート'!$A4="","",'入力シート'!C4),"") | D4: =IFERROR(IF('入力シート'!$A4="","",'入力シート'!D4),"") | E4: =IFERROR(IF('入力シート'!$A4="","",'入力シート'!I4),"") | F4: =IFERROR(IF('入力シート'!$A4="","",'入力シート'!N4),"") | G4: =IFERROR(IF('入力シート'!$A4="","",'入力シート'!O4),"") | H4: =IFERROR(IF('入力シート'!$A4="","",'入力シート'!P4),"") | I4: =IFERROR(IF('入力シート'!$A4="","",'入力シート'!Q4),"") | J4: =IFERROR(IF('入力シート'!$A4="","",'入力シート'!R4),"") | K4: =IFERROR(IF('入力シート'!$A4="","",IF(H4>='設定'!$B$4,"OK",IF(H4>='設定'!$B$5,"注意","要改善"))),"")
A5: =IFERROR(IF('入力シート'!$A5="","",'入力シート'!A5),"") | B5: =IFERROR(IF('入力シート'!$A5="","",'入力シート'!B5),"") | C5: =IFERROR(IF('入力シート'!$A5="","",'入力シート'!C5),"") | D5: =IFERROR(IF('入力シート'!$A5="","",'入力シート'!D5),"") | E5: =IFERROR(IF('入力シート'!$A5="","",'入力シート'!I5),"") | F5: =IFERROR(IF('入力シート'!$A5="","",'入力シート'!N5),"") | G5: =IFERROR(IF('入力シート'!$A5="","",'入力シート'!O5),"") | H5: =IFERROR(IF('入力シート'!$A5="","",'入力シート'!P5),"") | I5: =IFERROR(IF('入力シート'!$A5="","",'入力シート'!Q5),"") | J5: =IFERROR(IF('入力シート'!$A5="","",'入力シート'!R5),"") | K5: =IFERROR(IF('入力シート'!$A5="","",IF(H5>='設定'!$B$4,"OK",IF(H5>='設定'!$B$5,"注意","要改善"))),"")
A6: =IFERROR(IF('入力シート'!$A6="","",'入力シート'!A6),"") | B6: =IFERROR(IF('入力シート'!$A6="","",'入力シート'!B6),"") | C6: =IFERROR(IF('入力シート'!$A6="","",'入力シート'!C6),"") | D6: =IFERROR(IF('入力シート'!$A6="","",'入力シート'!D6),"") | E6: =IFERROR(IF('入力シート'!$A6="","",'入力シート'!I6),"") | F6: =IFERROR(IF('入力シート'!$A6="","",'入力シート'!N6),"") | G6: =IFERROR(IF('入力シート'!$A6="","",'入力シート'!O6),"") | H6: =IFERROR(IF('入力シート'!$A6="","",'入力シート'!P6),"") | I6: =IFERROR(IF('入力シート'!$A6="","",'入力シート'!Q6),"") | J6: =IFERROR(IF('入力シート'!$A6="","",'入力シート'!R6),"") | K6: =IFERROR(IF('入力シート'!$A6="","",IF(H6>='設定'!$B$4,"OK",IF(H6>='設定'!$B$5,"注意","要改善"))),"")
A7: =IFERROR(IF('入力シート'!$A7="","",'入力シート'!A7),"") | B7: =IFERROR(IF('入力シート'!$A7="","",'入力シート'!B7),"") | C7: =IFERROR(IF('入力シート'!$A7="","",'入力シート'!C7),"") | D7: =IFERROR(IF('入力シート'!$A7="","",'入力シート'!D7),"") | E7: =IFERROR(IF('入力シート'!$A7="","",'入力シート'!I7),"") | F7: =IFERROR(IF('入力シート'!$A7="","",'入力シート'!N7),"") | G7: =IFERROR(IF('入力シート'!$A7="","",'入力シート'!O7),"") | H7: =IFERROR(IF('入力シート'!$A7="","",'入力シート'!P7),"") | I7: =IFERROR(IF('入力シート'!$A7="","",'入力シート'!Q7),"") | J7: =IFERROR(IF('入力シート'!$A7="","",'入力シート'!R7),"") | K7: =IFERROR(IF('入力シート'!$A7="","",IF(H7>='設定'!$B$4,"OK",IF(H7>='設定'!$B$5,"注意","要改善"))),"")
A8: =IFERROR(IF('入力シート'!$A8="","",'入力シート'!A8),"") | B8: =IFERROR(IF('入力シート'!$A8="","",'入力シート'!B8),"") | C8: =IFERROR(IF('入力シート'!$A8="","",'入力シート'!C8),"") | D8: =IFERROR(IF('入力シート'!$A8="","",'入力シート'!D8),"") | E8: =IFERROR(IF('入力シート'!$A8="","",'入力シート'!I8),"") | F8: =IFERROR(IF('入力シート'!$A8="","",'入力シート'!N8),"") | G8: =IFERROR(IF('入力シート'!$A8="","",'入力シート'!O8),"") | H8: =IFERROR(IF('入力シート'!$A8="","",'入力シート'!P8),"") | I8: =IFERROR(IF('入力シート'!$A8="","",'入力シート'!Q8),"") | J8: =IFERROR(IF('入力シート'!$A8="","",'入力シート'!R8),"") | K8: =IFERROR(IF('入力シート'!$A8="","",IF(H8>='設定'!$B$4,"OK",IF(H8>='設定'!$B$5,"注意","要改善"))),"")
A9: =IFERROR(IF('入力シート'!$A9="","",'入力シート'!A9),"") | B9: =IFERROR(IF('入力シート'!$A9="","",'入力シート'!B9),"") | C9: =IFERROR(IF('入力シート'!$A9="","",'入力シート'!C9),"") | D9: =IFERROR(IF('入力シート'!$A9="","",'入力シート'!D9),"") | E9: =IFERROR(IF('入力シート'!$A9="","",'入力シート'!I9),"") | F9: =IFERROR(IF('入力シート'!$A9="","",'入力シート'!N9),"") | G9: =IFERROR(IF('入力シート'!$A9="","",'入力シート'!O9),"") | H9: =IFERROR(IF('入力シート'!$A9="","",'入力シート'!P9),"") | I9: =IFERROR(IF('入力シート'!$A9="","",'入力シート'!Q9),"") | J9: =IFERROR(IF('入力シート'!$A9="","",'入力シート'!R9),"") | K9: =IFERROR(IF('入力シート'!$A9="","",IF(H9>='設定'!$B$4,"OK",IF(H9>='設定'!$B$5,"注意","要改善"))),"")
A10: =IFERROR(IF('入力シート'!$A10="","",'入力シート'!A10),"") | B10: =IFERROR(IF('入力シート'!$A10="","",'入力シート'!B10),"") | C10: =IFERROR(IF('入力シート'!$A10="","",'入力シート'!C10),"") | D10: =IFERROR(IF('入力シート'!$A10="","",'入力シート'!D10),"") | E10: =IFERROR(IF('入力シート'!$A10="","",'入力シート'!I10),"") | F10: =IFERROR(IF('入力シート'!$A10="","",'入力シート'!N10),"") | G10: =IFERROR(IF('入力シート'!$A10="","",'入力シート'!O10),"") | H10: =IFERROR(IF('入力シート'!$A10="","",'入力シート'!P10),"") | I10: =IFERROR(IF('入力シート'!$A10="","",'入力シート'!Q10),"") | J10: =IFERROR(IF('入力シート'!$A10="","",'入力シート'!R10),"") | K10: =IFERROR(IF('入力シート'!$A10="","",IF(H10>='設定'!$B$4,"OK",IF(H10>='設定'!$B$5,"注意","要改善"))),"")
A11: =IFERROR(IF('入力シート'!$A11="","",'入力シート'!A11),"") | B11: =IFERROR(IF('入力シート'!$A11="","",'入力シート'!B11),"") | C11: =IFERROR(IF('入力シート'!$A11="","",'入力シート'!C11),"") | D11: =IFERROR(IF('入力シート'!$A11="","",'入力シート'!D11),"") | E11: =IFERROR(IF('入力シート'!$A11="","",'入力シート'!I11),"") | F11: =IFERROR(IF('入力シート'!$A11="","",'入力シート'!N11),"") | G11: =IFERROR(IF('入力シート'!$A11="","",'入力シート'!O11),"") | H11: =IFERROR(IF('入力シート'!$A11="","",'入力シート'!P11),"") | I11: =IFERROR(IF('入力シート'!$A11="","",'入力シート'!Q11),"") | J11: =IFERROR(IF('入力シート'!$A11="","",'入力シート'!R11),"") | K11: =IFERROR(IF('入力シート'!$A11="","",IF(H11>='設定'!$B$4,"OK",IF(H11>='設定'!$B$5,"注意","要改善"))),"")
A12: =IFERROR(IF('入力シート'!$A12="","",'入力シート'!A12),"") | B12: =IFERROR(IF('入力シート'!$A12="","",'入力シート'!B12),"") | C12: =IFERROR(IF('入力シート'!$A12="","",'入力シート'!C12),"") | D12: =IFERROR(IF('入力シート'!$A12="","",'入力シート'!D12),"") | E12: =IFERROR(IF('入力シート'!$A12="","",'入力シート'!I12),"") | F12: =IFERROR(IF('入力シート'!$A12="","",'入力シート'!N12),"") | G12: =IFERROR(IF('入力シート'!$A12="","",'入力シート'!O12),"") | H12: =IFERROR(IF('入力シート'!$A12="","",'入力シート'!P12),"") | I12: =IFERROR(IF('入力シート'!$A12="","",'入力シート'!Q12),"") | J12: =IFERROR(IF('入力シート'!$A12="","",'入力シート'!R12),"") | K12: =IFERROR(IF('入力シート'!$A12="","",IF(H12>='設定'!$B$4,"OK",IF(H12>='設定'!$B$5,"注意","要改善"))),"")
A13: =IFERROR(IF('入力シート'!$A13="","",'入力シート'!A13),"") | B13: =IFERROR(IF('入力シート'!$A13="","",'入力シート'!B13),"") | C13: =IFERROR(IF('入力シート'!$A13="","",'入力シート'!C13),"") | D13: =IFERROR(IF('入力シート'!$A13="","",'入力シート'!D13),"") | E13: =IFERROR(IF('入力シート'!$A13="","",'入力シート'!I13),"") | F13: =IFERROR(IF('入力シート'!$A13="","",'入力シート'!N13),"") | G13: =IFERROR(IF('入力シート'!$A13="","",'入力シート'!O13),"") | H13: =IFERROR(IF('入力シート'!$A13="","",'入力シート'!P13),"") | I13: =IFERROR(IF('入力シート'!$A13="","",'入力シート'!Q13),"") | J13: =IFERROR(IF('入力シート'!$A13="","",'入力シート'!R13),"") | K13: =IFERROR(IF('入力シート'!$A13="","",IF(H13>='設定'!$B$4,"OK",IF(H13>='設定'!$B$5,"注意","要改善"))),"")
... A301: =IFERROR(IF('入力シート'!$A301="","",'入力シート'!A301),"") | B301: =IFERROR(IF('入力シート'!$A301="","",'入力シート'!B301),"") | C301: =IFERROR(IF('入力シート'!$A301="","",'入力シート'!C301),"") | D301: =IFERROR(IF('入力シート'!$A301="","",'入力シート'!D301),"") | E301: =IFERROR(IF('入力シート'!$A301="","",'入力シート'!I301),"") | F301: =IFERROR(IF('入力シート'!$A301="","",'入力シート'!N301),"") | G301: =IFERROR(IF('入力シート'!$A301="","",'入力シート'!O301),"") | H301: =IFERROR(IF('入力シート'!$A301="","",'入力シート'!P301),"") | I301: =IFERROR(IF('入力シート'!$A301="","",'入力シート'!Q301),"") | J301: =IFERROR(IF('入力シート'!$A301="","",'入力シート'!R301),"") | K301: =IFERROR(IF('入力シート'!$A301="","",IF(H301>='設定'!$B$4,"OK",IF(H301>='設定'!$B$5,"注意","要改善"))),"")

Sheet 粗利分析
A1: 粗利分析ダッシュボード
A3: 項目 | B3: 金額・率 | C3: コメント
A4: お客様見積合計（税抜） | B4: ='社内実行予算書'!B18
A5: 社内実行予算合計 | B5: ='社内実行予算書'!C18
A6: 粗利額 | B6: ='社内実行予算書'!D18
A7: 粗利率 | B7: =IFERROR(B6/B4,0)
A8: 税込見積合計 | B8: ='お客様見積書'!D22
A9: 目標粗利率 | B9: ='設定'!$B$4
A11: 工区・部屋 | B11: お客様見積 | C11: 社内実行予算 | D11: 粗利額 | E11: 粗利率 | F11: 判定 | G11: 比率バー | H11: 備考
A12: ='社内実行予算書'!A4 | B12: ='社内実行予算書'!B4 | C12: ='社内実行予算書'!C4 | D12: ='社内実行予算書'!D4 | E12: ='社内実行予算書'!E4 | F12: ='社内実行予算書'!G4 | G12: ='社内実行予算書'!E4
A13: ='社内実行予算書'!A5 | B13: ='社内実行予算書'!B5 | C13: ='社内実行予算書'!C5 | D13: ='社内実行予算書'!D5 | E13: ='社内実行予算書'!E5 | F13: ='社内実行予算書'!G5 | G13: ='社内実行予算書'!E5
A14: ='社内実行予算書'!A6 | B14: ='社内実行予算書'!B6 | C14: ='社内実行予算書'!C6 | D14: ='社内実行予算書'!D6 | E14: ='社内実行予算書'!E6 | F14: ='社内実行予算書'!G6 | G14: ='社内実行予算書'!E6
A15: ='社内実行予算書'!A7 | B15: ='社内実行予算書'!B7 | C15: ='社内実行予算書'!C7 | D15: ='社内実行予算書'!D7 | E15: ='社内実行予算書'!E7 | F15: ='社内実行予算書'!G7 | G15: ='社内実行予算書'!E7
A16: ='社内実行予算書'!A8 | B16: ='社内実行予算書'!B8 | C16: ='社内実行予算書'!C8 | D16: ='社内実行予算書'!D8 | E16: ='社内実行予算書'!E8 | F16: ='社内実行予算書'!G8 | G16: ='社内実行予算書'!E8
A17: ='社内実行予算書'!A9 | B17: ='社内実行予算書'!B9 | C17: ='社内実行予算書'!C9 | D17: ='社内実行予算書'!D9 | E17: ='社内実行予算書'!E9 | F17: ='社内実行予算書'!G9 | G17: ='社内実行予算書'!E9
A18: ='社内実行予算書'!A10 | B18: ='社内実行予算書'!B10 | C18: ='社内実行予算書'!C10 | D18: ='社内実行予算書'!D10 | E18: ='社内実行予算書'!E10 | F18: ='社内実行予算書'!G10 | G18: ='社内実行予算書'!E10
A19: ='社内実行予算書'!A11 | B19: ='社内実行予算書'!B11 | C19: ='社内実行予算書'!C11 | D19: ='社内実行予算書'!D11 | E19: ='社内実行予算書'!E11 | F19: ='社内実行予算書'!G11 | G19: ='社内実行予算書'!E11
A20: ='社内実行予算書'!A12 | B20: ='社内実行予算書'!B12 | C20: ='社内実行予算書'!C12 | D20: ='社内実行予算書'!D12 | E20: ='社内実行予算書'!E12 | F20: ='社内実行予算書'!G12 | G20: ='社内実行予算書'!E12
A21: ='社内実行予算書'!A13 | B21: ='社内実行予算書'!B13 | C21: ='社内実行予算書'!C13 | D21: ='社内実行予算書'!D13 | E21: ='社内実行予算書'!E13 | F21: ='社内実行予算書'!G13 | G21: ='社内実行予算書'!E13
A22: ='社内実行予算書'!A14 | B22: ='社内実行予算書'!B14 | C22: ='社内実行予算書'!C14 | D22: ='社内実行予算書'!D14 | E22: ='社内実行予算書'!E14 | F22: ='社内実行予算書'!G14 | G22: ='社内実行予算書'!E14
A23: ='社内実行予算書'!A15 | B23: ='社内実行予算書'!B15 | C23: ='社内実行予算書'!C15 | D23: ='社内実行予算書'!D15 | E23: ='社内実行予算書'!E15 | F23: ='社内実行予算書'!G15 | G23: ='社内実行予算書'!E15
A24: ='社内実行予算書'!A16 | B24: ='社内実行予算書'!B16 | C24: ='社内実行予算書'!C16 | D24: ='社内実行予算書'!D16 | E24: ='社内実行予算書'!E16 | F24: ='社内実行予算書'!G16 | G24: ='社内実行予算書'!E16
A25: ='社内実行予算書'!A18 | B25: ='社内実行予算書'!B18 | C25: ='社内実行予算書'!C18 | D25: ='社内実行予算書'!D18 | E25: ='社内実行予算書'!E18 | F25: ='社内実行予算書'!G18 | G25: ='社内実行予算書'!E18
A27: カテゴリ別内訳（税抜）
A28: カテゴリ | B28: お客様金額 | C28: 実行予算 | D28: 粗利額 | E28: 粗利率
A29: 材料 | B29: =SUMIFS('入力シート'!$I$2:$I$301,'入力シート'!$C$2:$C$301,"材料",'入力シート'!$S$2:$S$301,"表示") | C29: =SUMIFS('入力シート'!$N$2:$N$301,'入力シート'!$C$2:$C$301,"材料",'入力シート'!$S$2:$S$301,"表示") | D29: =B29-C29 | E29: =IFERROR(D29/B29,0)
A30: 施工 | B30: =SUMIFS('入力シート'!$I$2:$I$301,'入力シート'!$C$2:$C$301,"施工",'入力シート'!$S$2:$S$301,"表示") | C30: =SUMIFS('入力シート'!$N$2:$N$301,'入力シート'!$C$2:$C$301,"施工",'入力シート'!$S$2:$S$301,"表示") | D30: =B30-C30 | E30: =IFERROR(D30/B30,0)
A31: 経費 | B31: =SUMIFS('入力シート'!$I$2:$I$301,'入力シート'!$C$2:$C$301,"経費",'入力シート'!$S$2:$S$301,"表示") | C31: =SUMIFS('入力シート'!$N$2:$N$301,'入力シート'!$C$2:$C$301,"経費",'入力シート'!$S$2:$S$301,"表示") | D31: =B31-C31 | E31: =IFERROR(D31/B31,0)
A32: 合計 | B32: =SUM(B29:B31) | C32: =SUM(C29:C31) | D32: =B32-C32 | E32: =IFERROR(D32/B32,0)
